Workbook

Sheet Dashboard
B2: Sales Performance Dashboard
B3: Jan 2024 – Dec 2025 | Customer Concentration • Discount & Margin Erosion • Regional Performance
B5: TOTAL REVENUE | E5: TOTAL NET PROFIT | H5: OVERALL MARGIN % | K5: TOP 10 CUSTOMERS' REV. SHARE | N5: DISCOUNT RATE INCREASE (24 MO) | Q5: SOUTH RETURN RATE vs. CO. AVG
B6: =Analysis_Data!B2 -> 1945626.1 | E6: =Analysis_Data!B3 -> 744281.38 | H6: =Analysis_Data!B4 -> 0.38254081 | K6: =Analysis_Data!G20 -> 0.33590926 | N6: =Analysis_Data!E59-Analysis_Data!E36 -> 0.15398747 | Q6: =Analysis_Data!E96-Analysis_Data!B6 -> 0.13646656
K8: Revenue concentration risk | N8: Margin pressure from discounting | Q8: vs. company-wide return rate
B10: Customer Revenue Concentration | K10: Discount Creep & Margin Erosion
B31: Regional Revenue Trend (South in Decline) | K31: Revenue vs. Return Rate by Region

Sheet Insights_Recommendations
B2: Insights & Recommendations
B4: Analysis based on 4,410 transactions, Jan 2024 – Dec 2025. All figures reference the live formulas in Analysis_Data and Sales_Transactions, so they update automatically if the underlying data changes.
B6: 1. Customer Revenue Concentration Risk
B7: Finding
B8: • The top 10 customers (5.6% of the 180-customer base) generate roughly 34% of total revenue, and the top 18 customers (10%) generate roughly 45%. Five of the top six accounts are tagged ‘Key Account,’ meaning a large share of revenue rests on a small number of relationships.
B9: • See the Pareto chart on the Dashboard — cumulative revenue share climbs steeply across the first 10–20 customers before flattening, the classic signature of concentration risk.
B10: Business Impact
B11: • Losing even one or two top accounts could meaningfully dent total revenue and profit with little warning, since the long tail of 160+ smaller customers cannot quickly absorb that gap.
B12: Recommended Actions
B13: • Set up an account health program (usage trend, satisfaction, renewal/reorder cadence) for the top 20 customers.
B14: • Assign named account owners and proactive check-ins for all ‘Key Account’-segment customers.
B15: • Invest in mid-tier (‘Standard’ segment) customer growth to diversify revenue away from the top 10.
... B37: • Set a target to bring South's return rate toward the ~5–6% company baseline, then track its revenue trend for recovery.

Sheet Overview
B2: Sales Transactions Dataset — Practice Case Study
B4: This workbook contains 2 years (Jan 2024 – Dec 2025) of order-level sales transactions for a multi-category retail business operating across 5 regions and 3 sales channels. The data is intentionally asymmetric — it reflects the kind of skewed, imperfect patterns found in real business datasets rather than a clean, evenly distributed sample.
B6: Dataset at a Glance
B7: • Rows (transactions): 4,410
B8: • Date range: 2024-01-01 to 2025-12-31
B9: • Regions: Central, East, North, South, West
B10: • Sales channels: Online, Retail, Wholesale
B11: • Product categories: Apparel, Electronics, Home & Kitchen, Office Supplies, Sporting Goods
B12: • Unique customers: 180
B14: Three Business Problems to Investigate
B15: The data has been generated so that each of the following issues is genuinely present and discoverable through analysis (pivot tables, charts, or formulas) — none of them are pre-solved in this workbook.
B17: 1. Customer Revenue Concentration Risk
... B29: • Quantity, pricing, and discount patterns vary by channel and category, as in real retail data.

Sheet Data_Dictionary
A1: Column | B1: Type | C1: Description
A2: Order_ID | B2: Text | C2: Unique order identifier (a few intentional duplicates present)
A3: Order_Date | B3: Date | C3: Date the order was placed
A4: Year | B4: Formula | C4: Year extracted from Order_Date
A5: Quarter | B5: Formula | C5: Calendar quarter extracted from Order_Date (Q1–Q4)
A6: Region | B6: Text | C6: Sales region: North, South, East, West, Central
A7: Sales_Channel | B7: Text | C7: Online, Retail, or Wholesale
A8: Sales_Rep | B8: Text | C8: Sales representative assigned to the order
A9: Customer_ID | B9: Text | C9: Unique customer identifier
A10: Customer_Name | B10: Text | C10: Customer name
A11: Customer_Segment | B11: Text | C11: Key Account / Standard / New & Occasional, based on historical order volume
A12: Product_Category | B12: Text | C12: Electronics, Home & Kitchen, Apparel, Sporting Goods, Office Supplies
... A24: Payment_Method | B24: Text | C24: Credit Card, Bank Transfer, PayPal, or Cash on Delivery

Sheet Sales_Transactions
A1: Order_ID | B1: Order_Date | C1: Year | D1: Quarter | E1: Region | F1: Sales_Channel | G1: Sales_Rep | H1: Customer_ID | I1: Customer_Name | J1: Customer_Segment | K1: Product_Category | L1: Product_Name | M1: Unit_Price | N1: Quantity | O1: Discount_Pct | P1: Unit_Cost | Q1: Revenue | R1: Discount_Amount | S1: COGS | T1: Net_Profit | U1: Margin_Pct | V1: Return_Flag | W1: Payment_Method
A2: ORD-00001 | B2: 45292 | C2: =YEAR(B2) -> 2024 | D2: ="Q"&ROUNDUP(MONTH(B2)/3,0) -> Q1 | E2: West | F2: Online | G2: Nourhan Aly | H2: CUST-0006 | I2: Mona Ibrahim | J2: Key Account | K2: Sporting Goods | L2: Resistance Bands | M2: 124.31 | N2: 3 | O2: 0.0657 | P2: 59.83 | Q2: =M2*N2*(1-O2) -> 348.4285 | R2: =M2*N2*O2 -> 24.501501 | S2: =P2*N2 -> 179.49 | T2: =Q2-S2 -> 168.9385 | U2: =IFERROR(T2/Q2,0) -> 0.48485844 | V2: No | W2: Credit Card
A3: ORD-00002 | B3: 45292 | C3: =YEAR(B3) -> 2024 | D3: ="Q"&ROUNDUP(MONTH(B3)/3,0) -> Q1 | E3: North | F3: Retail | G3: Tarek Aboul | H3: CUST-0016 | I3: Karim El-Masry | J3: Standard | K3: Home & Kitchen | L3: Vacuum Cleaner | M3: 84.75 | N3: 5 | O3: 0.0286 | P3: 44.15 | Q3: =M3*N3*(1-O3) -> 411.63075 | R3: =M3*N3*O3 -> 12.11925 | S3: =P3*N3 -> 220.75 | T3: =Q3-S3 -> 190.88075 | U3: =IFERROR(T3/Q3,0) -> 0.46371839 | V3: No | W3: Cash on Delivery
A4: ORD-00003 | B4: 45293 | C4: =YEAR(B4) -> 2024 | D4: ="Q"&ROUNDUP(MONTH(B4)/3,0) -> Q1 | E4: East | F4: Online | G4: Omar Said | H4: CUST-0137 | I4: Wael El-Sayed | J4: New / Occasional | K4: Electronics | L4: Noise-Cancel Headphones | M4: 296.74 | N4: 4 | O4: 0.1413 | P4: 196.46 | Q4: =M4*N4*(1-O4) -> 1019.2426 | R4: =M4*N4*O4 -> 167.71745 | S4: =P4*N4 -> 785.84 | T4: =Q4-S4 -> 233.40255 | U4: =IFERROR(T4/Q4,0) -> 0.22899608 | V4: No | W4: Cash on Delivery
A5: ORD-00004 | B5: 45293 | C5: =YEAR(B5) -> 2024 | D5: ="Q"&ROUNDUP(MONTH(B5)/3,0) -> Q1 | E5: East | F5: Online | G5: Yara Mostafa | H5: CUST-0008 | I5: Nour Ibrahim | J5: Key Account | K5: Office Supplies | L5: Desk Organizer | M5: 112.4 | N5: 1 | O5: 0.1513 | P5: 58.22 | Q5: =M5*N5*(1-O5) -> 95.39388 | R5: =M5*N5*O5 -> 17.00612 | S5: =P5*N5 -> 58.22 | T5: =Q5-S5 -> 37.17388 | U5: =IFERROR(T5/Q5,0) -> 0.38968831 | V5: No | W5: Credit Card
A6: ORD-00005 | B6: 45293 | C6: =YEAR(B6) -> 2024 | D6: ="Q"&ROUNDUP(MONTH(B6)/3,0) -> Q1 | E6: North | F6: Retail | G6: Mona Hassan | H6: CUST-0037 | I6: Mariam Aziz | J6: Standard | K6: Sporting Goods | L6: Bicycle Helmet | M6: 131.06 | N6: 2 | O6: 0.1 | P6: 62.45 | Q6: =M6*N6*(1-O6) -> 235.908 | R6: =M6*N6*O6 -> 26.212 | S6: =P6*N6 -> 124.9 | T6: =Q6-S6 -> 111.008 | U6: =IFERROR(T6/Q6,0) -> 0.47055632 | V6: No | W6: PayPal
A7: ORD-00006 | B7: 45293 | C7: =YEAR(B7) -> 2024 | D7: ="Q"&ROUNDUP(MONTH(B7)/3,0) -> Q1 | E7: South | F7: Wholesale | G7: Khaled Fathy | H7: CUST-0155 | I7: Reem Rashed | J7: New / Occasional | K7: Office Supplies | L7: Desk Organizer | M7: 207.78 | N7: 5 | O7: 0 | P7: 85.26 | Q7: =M7*N7*(1-O7) -> 1038.9 | R7: =M7*N7*O7 -> 0 | S7: =P7*N7 -> 426.3 | T7: =Q7-S7 -> 612.6 | U7: =IFERROR(T7/Q7,0) -> 0.58966214 | V7: No | W7: Cash on Delivery
A8: ORD-00007 | B8: 45293 | C8: =YEAR(B8) -> 2024 | D8: ="Q"&ROUNDUP(MONTH(B8)/3,0) -> Q1 | E8: South | F8: Retail | G8: Sara Adel | H8: CUST-0008 | I8: Nour Ibrahim | J8: Key Account | K8: Apparel | L8: Cotton T-Shirt Pack | M8: 96.73 | N8: 1 | O8: 0 | P8: 40.9 | Q8: =M8*N8*(1-O8) -> 96.73 | R8: =M8*N8*O8 -> 0 | S8: =P8*N8 -> 40.9 | T8: =Q8-S8 -> 55.83 | U8: =IFERROR(T8/Q8,0) -> 0.57717358 | V8: No | W8: PayPal
A9: ORD-00008 | B9: 45294 | C9: =YEAR(B9) -> 2024 | D9: ="Q"&ROUNDUP(MONTH(B9)/3,0) -> Q1 | E9: South | F9: Online | G9: Khaled Fathy | H9: CUST-0009 | I9: Reem Naguib | J9: Key Account | K9: Home & Kitchen | L9: Blender | M9: 87.17 | N9: 1 | O9: 0.1341 | P9: 52.93 | Q9: =M9*N9*(1-O9) -> 75.480503 | R9: =M9*N9*O9 -> 11.689497 | S9: =P9*N9 -> 52.93 | T9: =Q9-S9 -> 22.550503 | U9: =IFERROR(T9/Q9,0) -> 0.29875931 | V9: Yes | W9: Bank Transfer
A10: ORD-00009 | B10: 45294 | C10: =YEAR(B10) -> 2024 | D10: ="Q"&ROUNDUP(MONTH(B10)/3,0) -> Q1 | E10: North | F10: Wholesale | G10: Mona Hassan | H10: CUST-0084 | I10: Heba Soliman | J10: New / Occasional | K10: Office Supplies | L10: LED Desk Lamp | M10: 66.56 | N10: 48 | O10: 0.019 | P10: 34.37 | Q10: =M10*N10*(1-O10) -> 3134.1773 | R10: =M10*N10*O10 -> 60.70272 | S10: =P10*N10 -> 1649.76 | T10: =Q10-S10 -> 1484.4173 | U10: =IFERROR(T10/Q10,0) -> 0.47362263 | V10: No | W10: Bank Transfer
A11: ORD-00010 | B11: 45294 | C11: =YEAR(B11) -> 2024 | D11: ="Q"&ROUNDUP(MONTH(B11)/3,0) -> Q1 | E11: North | F11: Online | G11: Mona Hassan | H11: CUST-0027 | I11: Hassan El-Sayed | J11: Standard | K11: Apparel | L11: Winter Jacket | M11: 107.59 | N11: 3 | O11: 0.0883 | P11: 44.66 | Q11: =M11*N11*(1-O11) -> 294.26941 | R11: =M11*N11*O11 -> 28.500591 | S11: =P11*N11 -> 133.98 | T11: =Q11-S11 -> 160.28941 | U11: =IFERROR(T11/Q11,0) -> 0.54470293 | V11: No | W11: Credit Card
A12: ORD-00011 | B12: 45294 | C12: =YEAR(B12) -> 2024 | D12: ="Q"&ROUNDUP(MONTH(B12)/3,0) -> Q1 | E12: West | F12: Online | G12: Nourhan Aly | H12: CUST-0003 | I12: Nour Kamel | J12: Key Account | K12: Apparel | L12: Leather Belt | M12: 30.99 | N12: 12 | O12: 0.0493 | P12: 11.43 | Q12: =M12*N12*(1-O12) -> 353.54632 | R12: =M12*N12*O12 -> 18.333684 | S12: =P12*N12 -> 137.16 | T12: =Q12-S12 -> 216.38632 | U12: =IFERROR(T12/Q12,0) -> 0.61204517 | V12: No | W12: PayPal
A13: ORD-00012 | B13: 45294 | C13: =YEAR(B13) -> 2024 | D13: ="Q"&ROUNDUP(MONTH(B13)/3,0) -> Q1 | E13: East | F13: Retail | G13: Yara Mostafa | H13: CUST-0024 | I13: Reem Rashed | J13: Standard | K13: Office Supplies | L13: LED Desk Lamp | M13: 161.13 | N13: 4 | O13: 0.0338 | P13: 75.64 | Q13: =M13*N13*(1-O13) -> 622.73522 | R13: =M13*N13*O13 -> 21.784776 | S13: =P13*N13 -> 302.56 | T13: =Q13-S13 -> 320.17522 | U13: =IFERROR(T13/Q13,0) -> 0.51414343 | V13: No | W13: Credit Card
... A240: ORD-00239 | B240: 45340 | C240: =YEAR(B240) -> 2024 | D240: ="Q"&ROUNDUP(MONTH(B240)/3,0) -> Q1 | E240: Central | F240: Online | G240: Dina Magdy | H240: CUST-0050 | I240: Wael Farouk | J240: Standard | K240: Electronics | L240: Noise-Cancel Headphones | M240: 55.06 | N240: 4 | O240: 0.1118 | P240: 35.96 | Q240: =M240*N240*(1-O240) -> 195.61717 | R240: =M240*N240*O240 -> 24.622832 | S240: =P240*N240 -> 143.84 | T240: =Q240-S240 -> 51.777168 | U240: =IFERROR(T240/Q240,0) -> 0.26468622 | V240: No | W240: Credit Card
A241: ORD-00240 | B241: 45340 | C241: =YEAR(B241) -> 2024 | D241: ="Q"&ROUNDUP(MONTH(B241)/3,0) -> Q1 | E241: North | F241: Online | G241: Tarek Aboul | H241: CUST-0073 | I241: Dalia Ibrahim | J241: New / Occasional | K241: Electronics | L241: Wireless Mouse | M241: 51.44 | N241: 1 | P241: 32 | Q241: =M241*N241*(1-O241) -> 51.44 | R241: =M241*N241*O241 -> 0 | S241: =P241*N241 -> 32 | T241: =Q241-S241 -> 19.44 | U241: =IFERROR(T241/Q241,0) -> 0.37791602 | V241: No | W241: PayPal
A242: ORD-00241 | B242: 45340 | C242: =YEAR(B242) -> 2024 | D242: ="Q"&ROUNDUP(MONTH(B242)/3,0) -> Q1 | E242: South | F242: Retail | G242: Sara Adel | H242: CUST-0003 | I242: Nour Kamel | J242: Key Account | K242: Sporting Goods | L242: Adjustable Dumbbells | M242: 73.75 | N242: 1 | O242: 0.0632 | P242: 36.35 | Q242: =M242*N242*(1-O242) -> 69.089 | R242: =M242*N242*O242 -> 4.661 | S242: =P242*N242 -> 36.35 | T242: =Q242-S242 -> 32.739 | U242: =IFERROR(T242/Q242,0) -> 0.47386704 | V242: Yes | W242: Cash on Delivery
A243: ORD-00242 | B243: 45340 | C243: =YEAR(B243) -> 2024 | D243: ="Q"&ROUNDUP(MONTH(B243)/3,0) -> Q1 | E243: North | F243: Retail | G243: Tarek Aboul | H243: CUST-0005 | I243: Wael Farouk | J243: Key Account | K243: Sporting Goods | L243: Camping Tent | M243: 248.65 | N243: 8 | O243: 0.0571 | P243: 137.9 | Q243: =M243*N243*(1-O243) -> 1875.6167 | R243: =M243*N243*O243 -> 113.58332 | S243: =P243*N243 -> 1103.2 | T243: =Q243-S243 -> 772.41668 | U243: =IFERROR(T243/Q243,0) -> 0.41182012 | V243: No | W243: PayPal
A244: ORD-00243 | B244: 45340 | C244: =YEAR(B244) -> 2024 | D244: ="Q"&ROUNDUP(MONTH(B244)/3,0) -> Q1 | E244: North | F244: Retail | G244: Tarek Aboul | H244: CUST-0043 | I244: Sami Mansour | J244: Standard | K244: Sporting Goods | L244: Bicycle Helmet | M244: 113.91 | N244: 1 | O244: 0.0913 | P244: 63.7 | Q244: =M244*N244*(1-O244) -> 103.51002 | R244: =M244*N244*O244 -> 10.399983 | S244: =P244*N244 -> 63.7 | T244: =Q244-S244 -> 39.810017 | U244: =IFERROR(T244/Q244,0) -> 0.38460062 | V244: No | W244: Credit Card
A245: ORD-00244 | B245: 45340 | C245: =YEAR(B245) -> 2024 | D245: ="Q"&ROUNDUP(MONTH(B245)/3,0) -> Q1 | E245: South | F245: Online | G245: Khaled Fathy | H245: CUST-0061 | I245: Reem Ibrahim | J245: New / Occasional | K245: Sporting Goods | L245: Resistance Bands | M245: 104.21 | N245: 2 | O245: 0.1091 | P245: 59.86 | Q245: =M245*N245*(1-O245) -> 185.68138 | R245: =M245*N245*O245 -> 22.738622 | S245: =P245*N245 -> 119.72 | T245: =Q245-S245 -> 65.961378 | U245: =IFERROR(T245/Q245,0) -> 0.3552396 | V245: No | W245: PayPal
A246: ORD-00245 | B246: 45341 | C246: =YEAR(B246) -> 2024 | D246: ="Q"&ROUNDUP(MONTH(B246)/3,0) -> Q1 | E246: North | F246: Online | G246: Mona Hassan | H246: CUST-0017 | I246: Layla Mansour | J246: Standard | K246: Sporting Goods | L246: Adjustable Dumbbells | M246: 69.19 | N246: 5 | O246: 0.1083 | P246: 33.48 | Q246: =M246*N246*(1-O246) -> 308.48361 | R246: =M246*N246*O246 -> 37.466385 | S246: =P246*N246 -> 167.4 | T246: =Q246-S246 -> 141.08362 | U246: =IFERROR(T246/Q246,0) -> 0.45734557 | V246: No | W246: Cash on Delivery
A247: ORD-00246 | B247: 45341 | C247: =YEAR(B247) -> 2024 | D247: ="Q"&ROUNDUP(MONTH(B247)/3,0) -> Q1 | E247: South | F247: Online | G247: Khaled Fathy | H247: CUST-0008 | I247: Nour Ibrahim | J247: Key Account | K247: Office Supplies | L247: Printer Paper (Case) | M247: 123.92 | N247: 1 | O247: 0.1053 | P247: 63.32 | Q247: =M247*N247*(1-O247) -> 110.87122 | R247: =M247*N247*O247 -> 13.048776 | S247: =P247*N247 -> 63.32 | T247: =Q247-S247 -> 47.551224 | U247: =IFERROR(T247/Q247,0) -> 0.42888698 | V247: No | W247: Credit Card
A248: ORD-00247 | B248: 45341 | C248: =YEAR(B248) -> 2024 | D248: ="Q"&ROUNDUP(MONTH(B248)/3,0) -> Q1 | E248: North | F248: Wholesale | G248: Tarek Aboul | H248: CUST-0144 | I248: Adel El-Masry | J248: New / Occasional | K248: Apparel | L248: Winter Jacket | M248: 37.11 | N248: 5 | O248: 0 | P248: 14.27 | Q248: =M248*N248*(1-O248) -> 185.55 | R248: =M248*N248*O248 -> 0 | S248: =P248*N248 -> 71.35 | T248: =Q248-S248 -> 114.2 | U248: =IFERROR(T248/Q248,0) -> 0.61546753 | V248: No | W248: Cash on Delivery
A249: ORD-00248 | B249: 45341 | C249: =YEAR(B249) -> 2024 | D249: ="Q"&ROUNDUP(MONTH(B249)/3,0) -> Q1 | E249: North | F249: Online | G249: Tarek Aboul | H249: CUST-0131 | I249: Fady Abdallah | J249: New / Occasional | K249: Office Supplies | L249: Ergonomic Chair | M249: 48.95 | N249: 2 | O249: 0.153 | P249: 25.09 | Q249: =M249*N249*(1-O249) -> 82.9213 | R249: =M249*N249*O249 -> 14.9787 | S249: =P249*N249 -> 50.18 | T249: =Q249-S249 -> 32.7413 | U249: =IFERROR(T249/Q249,0) -> 0.39484789 | V249: No | W249: Credit Card
A250: ORD-00249 | B250: 45341 | C250: =YEAR(B250) -> 2024 | D250: ="Q"&ROUNDUP(MONTH(B250)/3,0) -> Q1 | E250: East | F250: Online | G250: Yara Mostafa | H250: CUST-0008 | I250: Nour Ibrahim | J250: Key Account | K250: Home & Kitchen | L250: Vacuum Cleaner | M250: 83.64 | N250: 1 | O250: 0.1128 | P250: 49.94 | Q250: =M250*N250*(1-O250) -> 74.205408 | R250: =M250*N250*O250 -> 9.434592 | S250: =P250*N250 -> 49.94 | T250: =Q250-S250 -> 24.265408 | U250: =IFERROR(T250/Q250,0) -> 0.32700323 | V250: No | W250: Credit Card
A251: ORD-00250 | B251: 45341 | C251: =YEAR(B251) -> 2024 | D251: ="Q"&ROUNDUP(MONTH(B251)/3,0) -> Q1 | E251: South | F251: Online | G251: Sara Adel | H251: CUST-0041 | I251: Nour El-Sayed | J251: Standard | K251: Apparel | L251: Denim Jeans | M251: 70.16 | N251: 2 | O251: 0.1393 | P251: 31.31 | Q251: =M251*N251*(1-O251) -> 120.77342 | R251: =M251*N251*O251 -> 19.546576 | S251: =P251*N251 -> 62.62 | T251: =Q251-S251 -> 58.153424 | U251: =IFERROR(T251/Q251,0) -> 0.48150845 | V251: No | W251: Bank Transfer
A252: ORD-00251 | B252: 45341 | C252: =YEAR(B252) -> 2024 | D252: ="Q"&ROUNDUP(MONTH(B252)/3,0) -> Q1 | E252: North | F252: Online | G252: Mona Hassan | H252: CUST-0079 | I252: Hassan Kamel | J252: New / Occasional | K252: Home & Kitchen | L252: Vacuum Cleaner | M252: 191.23 | N252: 1 | O252: 0.0637 | P252: 116.2 | Q252: =M252*N252*(1-O252) -> 179.04865 | R252: =M252*N252*O252 -> 12.181351 | S252: =P252*N252 -> 116.2 | T252: =Q252-S252 -> 62.848649 | U252: =IFERROR(T252/Q252,0) -> 0.35101437 | V252: No | W252: PayPal
A253: ORD-00252 | B253: 45341 | C253: =YEAR(B253) -> 2024 | D253: ="Q"&ROUNDUP(MONTH(B253)/3,0) -> Q1 | E253: North | F253: Retail | G253: Tarek Aboul | H253: CUST-0007 | I253: Hassan Naguib | J253: Key Account | K253: Office Supplies | L253: LED Desk Lamp | M253: 241.31 | N253: 1 | O253: 0.0411 | P253: 126.15 | Q253: =M253*N253*(1-O253) -> 231.39216 | R253: =M253*N253*O253 -> 9.917841 | S253: =P253*N253 -> 126.15 | T253: =Q253-S253 -> 105.24216 | U253: =IFERROR(T253/Q253,0) -> 0.45482163 | V253: No | W253: Bank Transfer
... A300: ORD-00299 | B300: 45351 | C300: =YEAR(B300) -> 2024 | D300: ="Q"&ROUNDUP(MONTH(B300)/3,0) -> Q1 | E300: South | F300: Online | G300: Khaled Fathy | H300: CUST-0035 | I300: Hassan Abdallah | J300: Standard | K300: Electronics | L300: Noise-Cancel Headphones | M300: 303.02 | N300: 2 | O300: 0.063 | P300: 173.16 | Q300: =M300*N300*(1-O300) -> 567.85948 | R300: =M300*N300*O300 -> 38.18052 | S300: =P300*N300 -> 346.32 | T300: =Q300-S300 -> 221.53948 | U300: =IFERROR(T300/Q300,0) -> 0.39013081 | V300: No | W300: Bank Transfer
A301: ORD-00300 | B301: 45351 | C301: =YEAR(B301) -> 2024 | D301: ="Q"&ROUNDUP(MONTH(B301)/3,0) -> Q1 | E301: North | F301: Online | G301: Mona Hassan | H301: CUST-0102 | I301: Layla Fahmy | J301: New / Occasional | K301: Electronics | L301: Noise-Cancel Headphones | M301: 257.45 | N301: 8 | P301: 147.83 | Q301: =M301*N301*(1-O301) -> 2059.6 | R301: =M301*N301*O301 -> 0 | S301: =P301*N301 -> 1182.64 | T301: =Q301-S301 -> 876.96 | U301: =IFERROR(T301/Q301,0) -> 0.42579142 | V301: No | W301: PayPal
A302: ORD-00301 | B302: 45351 | C302: =YEAR(B302) -> 2024 | D302: ="Q"&ROUNDUP(MONTH(B302)/3,0) -> Q1 | E302: South | F302: Retail | G302: Khaled Fathy | H302: CUST-0003 | I302: Nour Kamel | J302: Key Account | K302: Home & Kitchen | L302: Blender | M302: 38.67 | N302: 1 | O302: 0.0315 | P302: 21.01 | Q302: =M302*N302*(1-O302) -> 37.451895 | R302: =M302*N302*O302 -> 1.218105 | S302: =P302*N302 -> 21.01 | T302: =Q302-S302 -> 16.441895 | U302: =IFERROR(T302/Q302,0) -> 0.4390137 | V302: Yes | W302: Bank Transfer
A303: ORD-00302 | B303: 45352 | C303: =YEAR(B303) -> 2024 | D303: ="Q"&ROUNDUP(MONTH(B303)/3,0) -> Q1 | E303: South | F303: Online | G303: Sara Adel | H303: CUST-0018 | I303: Tamer Fahmy | J303: Standard | K303: Electronics | L303: Noise-Cancel Headphones | M303: 156.07 | N303: 4 | O303: 0.173 | P303: 88.35 | Q303: =M303*N303*(1-O303) -> 516.27956 | R303: =M303*N303*O303 -> 108.00044 | S303: =P303*N303 -> 353.4 | T303: =Q303-S303 -> 162.87956 | U303: =IFERROR(T303/Q303,0) -> 0.31548714 | V303: No | W303: Bank Transfer
A304: ORD-00303 | B304: 45352 | C304: =YEAR(B304) -> 2024 | D304: ="Q"&ROUNDUP(MONTH(B304)/3,0) -> Q1 | E304: East | F304: Retail | G304: Yara Mostafa | H304: CUST-0042 | I304: Youssef Soliman | J304: Standard | K304: Home & Kitchen | L304: Cookware Set | M304: 205.17 | N304: 3 | O304: 0.108 | P304: 113.3 | Q304: =M304*N304*(1-O304) -> 549.03492 | R304: =M304*N304*O304 -> 66.47508 | S304: =P304*N304 -> 339.9 | T304: =Q304-S304 -> 209.13492 | U304: =IFERROR(T304/Q304,0) -> 0.38091369 | V304: No | W304: Bank Transfer
A305: ORD-00304 | B305: 45352 | C305: =YEAR(B305) -> 2024 | D305: ="Q"&ROUNDUP(MONTH(B305)/3,0) -> Q1 | E305: Central | F305: Wholesale | G305: Ahmed Reda | H305: CUST-0075 | I305: Heba Sherif | J305: New / Occasional | K305: Sporting Goods | L305: Yoga Mat | M305: 175.62 | N305: 5 | O305: 0.0318 | P305: 85.19 | Q305: =M305*N305*(1-O305) -> 850.17642 | R305: =M305*N305*O305 -> 27.92358 | S305: =P305*N305 -> 425.95 | T305: =Q305-S305 -> 424.22642 | U305: =IFERROR(T305/Q305,0) -> 0.49898634 | V305: No | W305: Cash on Delivery
A306: ORD-00305 | B306: 45352 | C306: =YEAR(B306) -> 2024 | D306: ="Q"&ROUNDUP(MONTH(B306)/3,0) -> Q1 | E306: North | F306: Retail | G306: Tarek Aboul | H306: CUST-0003 | I306: Nour Kamel | J306: Key Account | K306: Apparel | L306: Denim Jeans | M306: 47.88 | N306: 2 | O306: 0.0408 | P306: 20.29 | Q306: =M306*N306*(1-O306) -> 91.852992 | R306: =M306*N306*O306 -> 3.907008 | S306: =P306*N306 -> 40.58 | T306: =Q306-S306 -> 51.272992 | U306: =IFERROR(T306/Q306,0) -> 0.5582071 | V306: No | W306: Credit Card
A307: ORD-00306 | B307: 45352 | C307: =YEAR(B307) -> 2024 | D307: ="Q"&ROUNDUP(MONTH(B307)/3,0) -> Q1 | E307: West | F307: Retail | G307: Nourhan Aly | H307: CUST-0009 | I307: Reem Naguib | J307: Key Account | K307: Electronics | L307: Smart Watch | M307: 108.93 | N307: 1 | O307: 0.091 | P307: 71.66 | Q307: =M307*N307*(1-O307) -> 99.01737 | R307: =M307*N307*O307 -> 9.91263 | S307: =P307*N307 -> 71.66 | T307: =Q307-S307 -> 27.35737 | U307: =IFERROR(T307/Q307,0) -> 0.27628859 | V307: No | W307: PayPal
A308: ORD-00307 | B308: 45352 | C308: =YEAR(B308) -> 2024 | D308: ="Q"&ROUNDUP(MONTH(B308)/3,0) -> Q1 | E308: East | F308: Retail | G308: Yara Mostafa | H308: CUST-0041 | I308: Nour El-Sayed | J308: Standard | K308: Apparel | L308: Leather Belt | M308: 78.96 | N308: 2 | O308: 0.0505 | P308: 35.93 | Q308: =M308*N308*(1-O308) -> 149.94504 | R308: =M308*N308*O308 -> 7.97496 | S308: =P308*N308 -> 71.86 | T308: =Q308-S308 -> 78.08504 | U308: =IFERROR(T308/Q308,0) -> 0.52075774 | V308: No | W308: Bank Transfer
A309: ORD-00308 | B309: 45352 | C309: =YEAR(B309) -> 2024 | D309: ="Q"&ROUNDUP(MONTH(B309)/3,0) -> Q1 | E309: North | F309: Wholesale | G309: Tarek Aboul | H309: CUST-0086 | I309: Fady Aziz | J309: New / Occasional | K309: Home & Kitchen | L309: Blender | M309: 101.77 | N309: 8 | O309: 0.0178 | P309: 52.19 | Q309: =M309*N309*(1-O309) -> 799.66795 | R309: =M309*N309*O309 -> 14.492048 | S309: =P309*N309 -> 417.52 | T309: =Q309-S309 -> 382.14795 | U309: =IFERROR(T309/Q309,0) -> 0.47788329 | V309: No | W309: PayPal
A310: ORD-00309 | B310: 45353 | C310: =YEAR(B310) -> 2024 | D310: ="Q"&ROUNDUP(MONTH(B310)/3,0) -> Q1 | E310: East | F310: Online | G310: Yara Mostafa | H310: CUST-0172 | I310: Omar El-Sayed | J310: New / Occasional | K310: Electronics | L310: Wireless Mouse | M310: 222.1 | N310: 1 | O310: 0.0651 | P310: 145.49 | Q310: =M310*N310*(1-O310) -> 207.64129 | R310: =M310*N310*O310 -> 14.45871 | S310: =P310*N310 -> 145.49 | T310: =Q310-S310 -> 62.15129 | U310: =IFERROR(T310/Q310,0) -> 0.29932048 | V310: No | W310: Bank Transfer
A311: ORD-00310 | B311: 45353 | C311: =YEAR(B311) -> 2024 | D311: ="Q"&ROUNDUP(MONTH(B311)/3,0) -> Q1 | E311: West | F311: Online | G311: Nourhan Aly | H311: CUST-0002 | I311: Sami Sherif | J311: Key Account | K311: Home & Kitchen | L311: Air Fryer | M311: 76.42 | N311: 1 | O311: 0.0785 | P311: 39.36 | Q311: =M311*N311*(1-O311) -> 70.42103 | R311: =M311*N311*O311 -> 5.99897 | S311: =P311*N311 -> 39.36 | T311: =Q311-S311 -> 31.06103 | U311: =IFERROR(T311/Q311,0) -> 0.44107605 | V311: No | W311: Credit Card
A312: ORD-00311 | B312: 45354 | C312: =YEAR(B312) -> 2024 | D312: ="Q"&ROUNDUP(MONTH(B312)/3,0) -> Q1 | E312: North | F312: Wholesale | G312: Mona Hassan | H312: CUST-0042 | I312: Youssef Soliman | J312: Standard | K312: Sporting Goods | L312: Bicycle Helmet | M312: 43.05 | N312: 5 | O312: 0.0389 | P312: 19.47 | Q312: =M312*N312*(1-O312) -> 206.87677 | R312: =M312*N312*O312 -> 8.373225 | S312: =P312*N312 -> 97.35 | T312: =Q312-S312 -> 109.52677 | U312: =IFERROR(T312/Q312,0) -> 0.52943002 | V312: No | W312: Cash on Delivery
A313: ORD-00312 | B313: 45354 | C313: =YEAR(B313) -> 2024 | D313: ="Q"&ROUNDUP(MONTH(B313)/3,0) -> Q1 | E313: Central | F313: Retail | G313: Dina Magdy | H313: CUST-0005 | I313: Wael Farouk | J313: Key Account | K313: Electronics | L313: Bluetooth Speaker | M313: 259.29 | N313: 4 | O313: 0.0321 | P313: 161.42 | Q313: =M313*N313*(1-O313) -> 1003.8672 | R313: =M313*N313*O313 -> 33.292836 | S313: =P313*N313 -> 645.68 | T313: =Q313-S313 -> 358.18716 | U313: =IFERROR(T313/Q313,0) -> 0.35680733 | V313: No | W313: Bank Transfer
... A347: ORD-00346 | B347: 45362 | C347: =YEAR(B347) -> 2024 | D347: ="Q"&ROUNDUP(MONTH(B347)/3,0) -> Q1 | E347: West | F347: Wholesale | G347: Hossam Zaki | H347: CUST-0007 | I347: Hassan Naguib | J347: Key Account | K347: Home & Kitchen | L347: Air Fryer | M347: 82.64 | N347: 15 | O347: 0.0345 | P347: 49.11 | Q347: =M347*N347*(1-O347) -> 1196.8338 | R347: =M347*N347*O347 -> 42.7662 | S347: =P347*N347 -> 736.65 | T347: =Q347-S347 -> 460.1838 | U347: =IFERROR(T347/Q347,0) -> 0.38450101 | V347: No | W347: Cash on Delivery
A348: ORD-00347 | B348: 45363 | C348: =YEAR(B348) -> 2024 | D348: ="Q"&ROUNDUP(MONTH(B348)/3,0) -> Q1 | E348: West | F348: Online | G348: Hossam Zaki | H348: CUST-0002 | I348: Sami Sherif | J348: Key Account | K348: Apparel | L348: Winter Jacket | M348: 71.74 | N348: 2 | P348: 32.4 | Q348: =M348*N348*(1-O348) -> 143.48 | R348: =M348*N348*O348 -> 0 | S348: =P348*N348 -> 64.8 | T348: =Q348-S348 -> 78.68 | U348: =IFERROR(T348/Q348,0) -> 0.54836911 | V348: No | W348: Cash on Delivery
A349: ORD-00348 | B349: 45363 | C349: =YEAR(B349) -> 2024 | D349: ="Q"&ROUNDUP(MONTH(B349)/3,0) -> Q1 | E349: East | F349: Retail | G349: Yara Mostafa | H349: CUST-0006 | I349: Mona Ibrahim | J349: Key Account | K349: Office Supplies | L349: LED Desk Lamp | M349: 204.26 | N349: 2 | O349: 0.1191 | P349: 98.2 | Q349: =M349*N349*(1-O349) -> 359.86527 | R349: =M349*N349*O349 -> 48.654732 | S349: =P349*N349 -> 196.4 | T349: =Q349-S349 -> 163.46527 | U349: =IFERROR(T349/Q349,0) -> 0.45424019 | V349: No | W349: PayPal
A350: ORD-00349 | B350: 45363 | C350: =YEAR(B350) -> 2024 | D350: ="Q"&ROUNDUP(MONTH(B350)/3,0) -> Q1 | E350: South | F350: Online | G350: Khaled Fathy | H350: CUST-0011 | I350: Nour Aziz | J350: Standard | K350: Office Supplies | L350: Printer Paper (Case) | M350: 273.3 | N350: 4 | O350: 0.0764 | P350: 113.13 | Q350: =M350*N350*(1-O350) -> 1009.6795 | R350: =M350*N350*O350 -> 83.52048 | S350: =P350*N350 -> 452.52 | T350: =Q350-S350 -> 557.15952 | U350: =IFERROR(T350/Q350,0) -> 0.55181818 | V350: No | W350: Bank Transfer
A351: ORD-00350 | B351: 45363 | C351: =YEAR(B351) -> 2024 | D351: ="Q"&ROUNDUP(MONTH(B351)/3,0) -> Q1 | E351: East | F351: Retail | G351: Omar Said | H351: CUST-0043 | I351: Sami Mansour | J351: Standard | K351: Apparel | L351: Winter Jacket | M351: 17.04 | N351: 5 | P351: 7.23 | Q351: =M351*N351*(1-O351) -> 85.2 | R351: =M351*N351*O351 -> 0 | S351: =P351*N351 -> 36.15 | T351: =Q351-S351 -> 49.05 | U351: =IFERROR(T351/Q351,0) -> 0.57570423 | V351: No | W351: Cash on Delivery
A352: ORD-00351 | B352: 45363 | C352: =YEAR(B352) -> 2024 | D352: ="Q"&ROUNDUP(MONTH(B352)/3,0) -> Q1 | E352: North | F352: Online | G352: Mona Hassan | H352: CUST-0004 | I352: Layla Mansour | J352: Key Account | K352: Sporting Goods | L352: Camping Tent | M352: 202.81 | N352: 1 | O352: 0.107 | P352: 107.69 | Q352: =M352*N352*(1-O352) -> 181.10933 | R352: =M352*N352*O352 -> 21.70067 | S352: =P352*N352 -> 107.69 | T352: =Q352-S352 -> 73.41933 | U352: =IFERROR(T352/Q352,0) -> 0.40538679 | V352: No | W352: Credit Card
A353: ORD-00352 | B353: 45363 | C353: =YEAR(B353) -> 2024 | D353: ="Q"&ROUNDUP(MONTH(B353)/3,0) -> Q1 | E353: East | F353: Online | G353: Yara Mostafa | H353: CUST-0005 | I353: Wael Farouk | J353: Key Account | K353: Home & Kitchen | L353: Cookware Set | M353: 204.08 | N353: 1 | O353: 0.0866 | P353: 104.81 | Q353: =M353*N353*(1-O353) -> 186.40667 | R353: =M353*N353*O353 -> 17.673328 | S353: =P353*N353 -> 104.81 | T353: =Q353-S353 -> 81.596672 | U353: =IFERROR(T353/Q353,0) -> 0.43773472 | V353: No | W353: Credit Card
A354: ORD-00353 | B354: 45364 | C354: =YEAR(B354) -> 2024 | D354: ="Q"&ROUNDUP(MONTH(B354)/3,0) -> Q1 | E354: South | F354: Online | G354: Khaled Fathy | H354: CUST-0019 | I354: Salma Hamdy | J354: Standard | K354: Sporting Goods | L354: Camping Tent | M354: 196.97 | N354: 1 | O354: 0.098 | P354: 101.98 | Q354: =M354*N354*(1-O354) -> 177.66694 | R354: =M354*N354*O354 -> 19.30306 | S354: =P354*N354 -> 101.98 | T354: =Q354-S354 -> 75.68694 | U354: =IFERROR(T354/Q354,0) -> 0.42600464 | V354: No | W354: Bank Transfer
A355: ORD-00354 | B355: 45364 | C355: =YEAR(B355) -> 2024 | D355: ="Q"&ROUNDUP(MONTH(B355)/3,0) -> Q1 | E355: Central | F355: Retail | G355: Ahmed Reda | H355: CUST-0001 | I355: Layla Ibrahim | J355: Key Account | K355: Apparel | L355: Cotton T-Shirt Pack | M355: 113.46 | N355: 1 | O355: 0.0183 | P355: 54.81 | Q355: =M355*N355*(1-O355) -> 111.38368 | R355: =M355*N355*O355 -> 2.076318 | S355: =P355*N355 -> 54.81 | T355: =Q355-S355 -> 56.573682 | U355: =IFERROR(T355/Q355,0) -> 0.50791715 | V355: Yes | W355: Bank Transfer
A356: ORD-00355 | B356: 45364 | C356: =YEAR(B356) -> 2024 | D356: ="Q"&ROUNDUP(MONTH(B356)/3,0) -> Q1 | E356: West | F356: Online | G356: Nourhan Aly | H356: CUST-0128 | I356: Mona El-Sayed | J356: New / Occasional | K356: Apparel | L356: Running Shoes | M356: 39.72 | N356: 2 | O356: 0.1508 | P356: 17.52 | Q356: =M356*N356*(1-O356) -> 67.460448 | R356: =M356*N356*O356 -> 11.979552 | S356: =P356*N356 -> 35.04 | T356: =Q356-S356 -> 32.420448 | U356: =IFERROR(T356/Q356,0) -> 0.48058453 | V356: No | W356: Cash on Delivery
A357: ORD-00356 | B357: 45364 | C357: =YEAR(B357) -> 2024 | D357: ="Q"&ROUNDUP(MONTH(B357)/3,0) -> Q1 | E357: Central | F357: Online | G357: Laila Younis | H357: CUST-0015 | I357: Sami Kamel | J357: Standard | K357: Home & Kitchen | L357: Coffee Maker | M357: 180.03 | N357: 1 | O357: 0.1247 | P357: 98.92 | Q357: =M357*N357*(1-O357) -> 157.58026 | R357: =M357*N357*O357 -> 22.449741 | S357: =P357*N357 -> 98.92 | T357: =Q357-S357 -> 58.660259 | U357: =IFERROR(T357/Q357,0) -> 0.37225639 | V357: No | W357: Credit Card
A358: ORD-00357 | B358: 45364 | C358: =YEAR(B358) -> 2024 | D358: ="Q"&ROUNDUP(MONTH(B358)/3,0) -> Q1 | E358: West | F358: Retail | G358: Hossam Zaki | H358: CUST-0151 | I358: Salma Rashed | J358: New / Occasional | K358: Electronics | L358: Noise-Cancel Headphones | M358: 71.12 | N358: 1 | O358: 0.0836 | P358: 41.15 | Q358: =M358*N358*(1-O358) -> 65.174368 | R358: =M358*N358*O358 -> 5.945632 | S358: =P358*N358 -> 41.15 | T358: =Q358-S358 -> 24.024368 | U358: =IFERROR(T358/Q358,0) -> 0.36861682 | V358: No | W358: PayPal
A359: ORD-00358 | B359: 45364 | C359: =YEAR(B359) -> 2024 | D359: ="Q"&ROUNDUP(MONTH(B359)/3,0) -> Q1 | E359: East | F359: Online | G359: Yara Mostafa | H359: CUST-0006 | I359: Mona Ibrahim | J359: Key Account | K359: Electronics | L359: USB-C Hub | M359: 207.34 | N359: 2 | O359: 0.1022 | P359: 116.31 | Q359: =M359*N359*(1-O359) -> 372.2997 | R359: =M359*N359*O359 -> 42.380296 | S359: =P359*N359 -> 232.62 | T359: =Q359-S359 -> 139.6797 | U359: =IFERROR(T359/Q359,0) -> 0.37518081 | V359: No | W359: Cash on Delivery
A360: ORD-00359 | B360: 45365 | C360: =YEAR(B360) -> 2024 | D360: ="Q"&ROUNDUP(MONTH(B360)/3,0) -> Q1 | E360: West | F360: Retail | G360: Hossam Zaki | H360: CUST-0039 | I360: Reem Sherif | J360: Standard | K360: Electronics | L360: Wireless Mouse | M360: 72.79 | N360: 1 | O360: 0.0923 | P360: 42.19 | Q360: =M360*N360*(1-O360) -> 66.071483 | R360: =M360*N360*O360 -> 6.718517 | S360: =P360*N360 -> 42.19 | T360: =Q360-S360 -> 23.881483 | U360: =IFERROR(T360/Q360,0) -> 0.36144917 | V360: No | W360: PayPal
A361: ORD-00360 | B361: 45366 | C361: =YEAR(B361) -> 2024 | D361: ="Q"&ROUNDUP(MONTH(B361)/3,0) -> Q1 | E361: North | F361: Retail | G361: Mona Hassan | H361: CUST-0033 | I361: Salma Hamdy | J361: Standard | K361: Office Supplies | L361: Standing Desk | M361: 303.74 | N361: 1 | O361: 0.1137 | P361: 152.75 | Q361: =M361*N361*(1-O361) -> 269.20476 | R361: =M361*N361*O361 -> 34.535238 | S361: =P361*N361 -> 152.75 | T361: =Q361-S361 -> 116.45476 | U361: =IFERROR(T361/Q361,0) -> 0.43258805 | V361: No | W361: PayPal
A362: ORD-00361 | B362: 45366 | C362: =YEAR(B362) -> 2024 | D362: ="Q"&ROUNDUP(MONTH(B362)/3,0) -> Q1 | E362: North | F362: Online | G362: Tarek Aboul | H362: CUST-0044 | I362: Karim El-Masry | J362: Standard | K362: Sporting Goods | L362: Bicycle Helmet | M362: 209.97 | N362: 3 | O362: 0.1318 | P362: 112.2 | Q362: =M362*N362*(1-O362) -> 546.88786 | R362: =M362*N362*O362 -> 83.022138 | S362: =P362*N362 -> 336.6 | T362: =Q362-S362 -> 210.28786 | U362: =IFERROR(T362/Q362,0) -> 0.38451733 | V362: No | W362: Credit Card
A363: ORD-00362 | B363: 45366 | C363: =YEAR(B363) -> 2024 | D363: ="Q"&ROUNDUP(MONTH(B363)/3,0) -> Q1 | E363: North | F363: Online | G363: Tarek Aboul | H363: CUST-0058 | I363: Tamer Soliman | J363: Standard | K363: Sporting Goods | L363: Camping Tent | M363: 14.22 | N363: 2 | O363: 0.0125 | P363: 7.64 | Q363: =M363*N363*(1-O363) -> 28.0845 | R363: =M363*N363*O363 -> 0.3555 | S363: =P363*N363 -> 15.28 | T363: =Q363-S363 -> 12.8045 | U363: =IFERROR(T363/Q363,0) -> 0.45592765 | V363: No | W363: Credit Card
... A376: ORD-00375 | B376: 45368 | C376: =YEAR(B376) -> 2024 | D376: ="Q"&ROUNDUP(MONTH(B376)/3,0) -> Q1 | E376: East | F376: Wholesale | G376: Omar Said | H376: CUST-0026 | I376: Wael Naguib | J376: Standard | K376: Home & Kitchen | L376: Coffee Maker | M376: 57.38 | N376: 10 | O376: 0.0635 | P376: 31.18 | Q376: =M376*N376*(1-O376) -> 537.3637 | R376: =M376*N376*O376 -> 36.4363 | S376: =P376*N376 -> 311.8 | T376: =Q376-S376 -> 225.5637 | U376: =IFERROR(T376/Q376,0) -> 0.41975984 | V376: No | W376: Bank Transfer
A377: ORD-00376 | B377: 45368 | C377: =YEAR(B377) -> 2024 | D377: ="Q"&ROUNDUP(MONTH(B377)/3,0) -> Q1 | E377: West | F377: Online | G377: Hossam Zaki | H377: CUST-0121 | I377: Mona Abdallah | J377: New / Occasional | K377: Sporting Goods | L377: Adjustable Dumbbells | M377: 124.3 | N377: 4 | P377: 57.88 | Q377: =M377*N377*(1-O377) -> 497.2 | R377: =M377*N377*O377 -> 0 | S377: =P377*N377 -> 231.52 | T377: =Q377-S377 -> 265.68 | U377: =IFERROR(T377/Q377,0) -> 0.53435237 | V377: No | W377: PayPal
A378: ORD-00377 | B378: 45368 | C378: =YEAR(B378) -> 2024 | D378: ="Q"&ROUNDUP(MONTH(B378)/3,0) -> Q1 | E378: South | F378: Online | G378: Sara Adel | H378: CUST-0003 | I378: Nour Kamel | J378: Key Account | K378: Electronics | L378: Noise-Cancel Headphones | M378: 76 | N378: 5 | O378: 0.17 | P378: 51.53 | Q378: =M378*N378*(1-O378) -> 315.4 | R378: =M378*N378*O378 -> 64.6 | S378: =P378*N378 -> 257.65 | T378: =Q378-S378 -> 57.75 | U378: =IFERROR(T378/Q378,0) -> 0.18310082 | V378: No | W378: Bank Transfer
A379: ORD-00378 | B379: 45369 | C379: =YEAR(B379) -> 2024 | D379: ="Q"&ROUNDUP(MONTH(B379)/3,0) -> Q1 | E379: West | F379: Retail | G379: Nourhan Aly | H379: CUST-0003 | I379: Nour Kamel | J379: Key Account | K379: Sporting Goods | L379: Camping Tent | M379: 165.17 | N379: 1 | O379: 0.0724 | P379: 84.9 | Q379: =M379*N379*(1-O379) -> 153.21169 | R379: =M379*N379*O379 -> 11.958308 | S379: =P379*N379 -> 84.9 | T379: =Q379-S379 -> 68.311692 | U379: =IFERROR(T379/Q379,0) -> 0.44586475 | V379: No | W379: PayPal
A380: ORD-00379 | B380: 45369 | C380: =YEAR(B380) -> 2024 | D380: ="Q"&ROUNDUP(MONTH(B380)/3,0) -> Q1 | E380: North | F380: Retail | G380: Tarek Aboul | H380: CUST-0006 | I380: Mona Ibrahim | J380: Key Account | K380: Apparel | L380: Leather Belt | M380: 70.64 | N380: 2 | O380: 0.0461 | P380: 33.98 | Q380: =M380*N380*(1-O380) -> 134.76699 | R380: =M380*N380*O380 -> 6.513008 | S380: =P380*N380 -> 67.96 | T380: =Q380-S380 -> 66.806992 | U380: =IFERROR(T380/Q380,0) -> 0.49572222 | V380: No | W380: Cash on Delivery
A381: ORD-00380 | B381: 45369 | C381: =YEAR(B381) -> 2024 | D381: ="Q"&ROUNDUP(MONTH(B381)/3,0) -> Q1 | E381: North | F381: Wholesale | G381: Mona Hassan | H381: CUST-0110 | I381: Reem Aziz | J381: New / Occasional | K381: Sporting Goods | L381: Bicycle Helmet | M381: 101.32 | N381: 15 | O381: 0.0428 | P381: 54.2 | Q381: =M381*N381*(1-O381) -> 1454.7526 | R381: =M381*N381*O381 -> 65.04744 | S381: =P381*N381 -> 813 | T381: =Q381-S381 -> 641.75256 | U381: =IFERROR(T381/Q381,0) -> 0.44114207 | V381: No | W381: Cash on Delivery
A382: ORD-00381 | B382: 45370 | C382: =YEAR(B382) -> 2024 | D382: ="Q"&ROUNDUP(MONTH(B382)/3,0) -> Q1 | E382: East | F382: Online | G382: Omar Said | H382: CUST-0002 | I382: Sami Sherif | J382: Key Account | K382: Electronics | L382: USB-C Hub | M382: 162.57 | N382: 1 | O382: 0.1374 | P382: 109.23 | Q382: =M382*N382*(1-O382) -> 140.23288 | R382: =M382*N382*O382 -> 22.337118 | S382: =P382*N382 -> 109.23 | T382: =Q382-S382 -> 31.002882 | U382: =IFERROR(T382/Q382,0) -> 0.2210814 | V382: Yes | W382: PayPal
A383: ORD-00382 | B383: 45370 | C383: =YEAR(B383) -> 2024 | D383: ="Q"&ROUNDUP(MONTH(B383)/3,0) -> Q1 | E383: East | F383: Wholesale | G383: Omar Said | H383: CUST-0026 | I383: Wael Naguib | J383: Standard | K383: Home & Kitchen | L383: Blender | M383: 212.25 | N383: 4 | O383: 0.0189 | P383: 117.81 | Q383: =M383*N383*(1-O383) -> 832.9539 | R383: =M383*N383*O383 -> 16.0461 | S383: =P383*N383 -> 471.24 | T383: =Q383-S383 -> 361.7139 | U383: =IFERROR(T383/Q383,0) -> 0.4342544 | V383: No | W383: Credit Card
A384: ORD-00383 | B384: 45370 | C384: =YEAR(B384) -> 2024 | D384: ="Q"&ROUNDUP(MONTH(B384)/3,0) -> Q1 | E384: Central | F384: Retail | G384: Laila Younis | H384: CUST-0025 | I384: Hala Hamdy | J384: Standard | K384: Office Supplies | L384: Ergonomic Chair | M384: 287.33 | N384: 1 | O384: 0.116 | P384: 139.18 | Q384: =M384*N384*(1-O384) -> 253.99972 | R384: =M384*N384*O384 -> 33.33028 | S384: =P384*N384 -> 139.18 | T384: =Q384-S384 -> 114.81972 | U384: =IFERROR(T384/Q384,0) -> 0.45204664 | V384: No | W384: PayPal
A385: ORD-00384 | B385: 45370 | C385: =YEAR(B385) -> 2024 | D385: ="Q"&ROUNDUP(MONTH(B385)/3,0) -> Q1 | E385: West | F385: Online | G385: Hossam Zaki | H385: CUST-0063 | I385: Youssef Fahmy | J385: New / Occasional | K385: Office Supplies | L385: Printer Paper (Case) | M385: 273 | N385: 1 | O385: 0.1136 | P385: 126.5 | Q385: =M385*N385*(1-O385) -> 241.9872 | R385: =M385*N385*O385 -> 31.0128 | S385: =P385*N385 -> 126.5 | T385: =Q385-S385 -> 115.4872 | U385: =IFERROR(T385/Q385,0) -> 0.47724508 | V385: Yes | W385: Credit Card
A386: ORD-00385 | B386: 45370 | C386: =YEAR(B386) -> 2024 | D386: ="Q"&ROUNDUP(MONTH(B386)/3,0) -> Q1 | E386: East | F386: Retail | G386: Omar Said | H386: CUST-0018 | I386: Tamer Fahmy | J386: Standard | K386: Office Supplies | L386: Printer Paper (Case) | M386: 307.52 | N386: 1 | O386: 0.1129 | P386: 141.34 | Q386: =M386*N386*(1-O386) -> 272.80099 | R386: =M386*N386*O386 -> 34.719008 | S386: =P386*N386 -> 141.34 | T386: =Q386-S386 -> 131.46099 | U386: =IFERROR(T386/Q386,0) -> 0.48189338 | V386: No | W386: Cash on Delivery
A387: ORD-00386 | B387: 45370 | C387: =YEAR(B387) -> 2024 | D387: ="Q"&ROUNDUP(MONTH(B387)/3,0) -> Q1 | E387: North | F387: Retail | G387: Mona Hassan | H387: CUST-0008 | I387: Nour Ibrahim | J387: Key Account | K387: Home & Kitchen | L387: Vacuum Cleaner | M387: 27.84 | N387: 4 | O387: 0.1386 | P387: 15.83 | Q387: =M387*N387*(1-O387) -> 95.925504 | R387: =M387*N387*O387 -> 15.434496 | S387: =P387*N387 -> 63.32 | T387: =Q387-S387 -> 32.605504 | U387: =IFERROR(T387/Q387,0) -> 0.33990443 | V387: No | W387: PayPal
A388: ORD-00387 | B388: 45371 | C388: =YEAR(B388) -> 2024 | D388: ="Q"&ROUNDUP(MONTH(B388)/3,0) -> Q1 | E388: North | F388: Retail | G388: Mona Hassan | H388: CUST-0077 | I388: Wael Mansour | J388: New / Occasional | K388: Office Supplies | L388: Standing Desk | M388: 196.21 | N388: 1 | O388: 0.0613 | P388: 93.52 | Q388: =M388*N388*(1-O388) -> 184.18233 | R388: =M388*N388*O388 -> 12.027673 | S388: =P388*N388 -> 93.52 | T388: =Q388-S388 -> 90.662327 | U388: =IFERROR(T388/Q388,0) -> 0.49224227 | V388: No | W388: PayPal
A389: ORD-00388 | B389: 45371 | C389: =YEAR(B389) -> 2024 | D389: ="Q"&ROUNDUP(MONTH(B389)/3,0) -> Q1 | E389: West | F389: Online | G389: Hossam Zaki | H389: CUST-0107 | I389: Tamer El-Masry | J389: New / Occasional | K389: Home & Kitchen | L389: Air Fryer | M389: 43.98 | N389: 1 | O389: 0.1511 | P389: 22.4 | Q389: =M389*N389*(1-O389) -> 37.334622 | R389: =M389*N389*O389 -> 6.645378 | S389: =P389*N389 -> 22.4 | T389: =Q389-S389 -> 14.934622 | U389: =IFERROR(T389/Q389,0) -> 0.40002071 | V389: No | W389: Cash on Delivery
... A519: ORD-00518 | B519: 45395 | C519: =YEAR(B519) -> 2024 | D519: ="Q"&ROUNDUP(MONTH(B519)/3,0) -> Q2 | E519: West | F519: Online | G519: Nourhan Aly | H519: CUST-0065 | I519: Mariam Aziz | J519: New / Occasional | K519: Sporting Goods | L519: Resistance Bands | M519: 254.15 | N519: 3 | O519: 0.1376 | P519: 117.66 | Q519: =M519*N519*(1-O519) -> 657.53688 | R519: =M519*N519*O519 -> 104.91312 | S519: =P519*N519 -> 352.98 | T519: =Q519-S519 -> 304.55688 | U519: =IFERROR(T519/Q519,0) -> 0.4631784 | V519: No | W519: Credit Card
A520: ORD-00519 | B520: 45395 | C520: =YEAR(B520) -> 2024 | D520: ="Q"&ROUNDUP(MONTH(B520)/3,0) -> Q2 | E520: West | F520: Retail | G520: Nourhan Aly | H520: CUST-0146 | I520: Adel Fahmy | J520: New / Occasional | K520: Office Supplies | L520: Desk Organizer | M520: 152.4 | N520: 2 | P520: 70.19 | Q520: =M520*N520*(1-O520) -> 304.8 | R520: =M520*N520*O520 -> 0 | S520: =P520*N520 -> 140.38 | T520: =Q520-S520 -> 164.42 | U520: =IFERROR(T520/Q520,0) -> 0.5394357 | V520: No | W520: Credit Card
A521: ORD-00520 | B521: 45395 | C521: =YEAR(B521) -> 2024 | D521: ="Q"&ROUNDUP(MONTH(B521)/3,0) -> Q2 | E521: North | F521: Retail | G521: Tarek Aboul | H521: CUST-0062 | I521: Layla Gad | J521: New / Occasional | K521: Office Supplies | L521: Ergonomic Chair | M521: 37.4 | N521: 4 | O521: 0.0192 | P521: 17.94 | Q521: =M521*N521*(1-O521) -> 146.72768 | R521: =M521*N521*O521 -> 2.87232 | S521: =P521*N521 -> 71.76 | T521: =Q521-S521 -> 74.96768 | U521: =IFERROR(T521/Q521,0) -> 0.51093073 | V521: No | W521: Cash on Delivery
A522: ORD-00521 | B522: 45396 | C522: =YEAR(B522) -> 2024 | D522: ="Q"&ROUNDUP(MONTH(B522)/3,0) -> Q2 | E522: North | F522: Wholesale | G522: Mona Hassan | H522: CUST-0060 | I522: Fady Gad | J522: Standard | K522: Apparel | L522: Winter Jacket | M522: 125.46 | N522: 25 | O522: 0.0732 | P522: 55.27 | Q522: =M522*N522*(1-O522) -> 2906.9082 | R522: =M522*N522*O522 -> 229.5918 | S522: =P522*N522 -> 1381.75 | T522: =Q522-S522 -> 1525.1582 | U522: =IFERROR(T522/Q522,0) -> 0.52466679 | V522: No | W522: Bank Transfer
A523: ORD-00522 | B523: 45396 | C523: =YEAR(B523) -> 2024 | D523: ="Q"&ROUNDUP(MONTH(B523)/3,0) -> Q2 | E523: East | F523: Online | G523: Omar Said | H523: CUST-0030 | I523: Layla Soliman | J523: Standard | K523: Office Supplies | L523: Ergonomic Chair | M523: 41.98 | N523: 4 | O523: 0.1176 | P523: 19.4 | Q523: =M523*N523*(1-O523) -> 148.17261 | R523: =M523*N523*O523 -> 19.747392 | S523: =P523*N523 -> 77.6 | T523: =Q523-S523 -> 70.572608 | U523: =IFERROR(T523/Q523,0) -> 0.47628647 | V523: No | W523: Bank Transfer
A524: ORD-00523 | B524: 45396 | C524: =YEAR(B524) -> 2024 | D524: ="Q"&ROUNDUP(MONTH(B524)/3,0) -> Q2 | E524: North | F524: Retail | G524: Mona Hassan | H524: CUST-0164 | I524: Hassan Farouk | J524: New / Occasional | K524: Electronics | L524: Noise-Cancel Headphones | M524: 241.38 | N524: 1 | O524: 0.0679 | P524: 148.58 | Q524: =M524*N524*(1-O524) -> 224.9903 | R524: =M524*N524*O524 -> 16.389702 | S524: =P524*N524 -> 148.58 | T524: =Q524-S524 -> 76.410298 | U524: =IFERROR(T524/Q524,0) -> 0.33961597 | V524: No | W524: Cash on Delivery
A525: ORD-00524 | B525: 45396 | C525: =YEAR(B525) -> 2024 | D525: ="Q"&ROUNDUP(MONTH(B525)/3,0) -> Q2 | E525: East | F525: Retail | G525: Omar Said | H525: CUST-0012 | I525: Wael Gad | J525: Standard | K525: Apparel | L525: Winter Jacket | M525: 111.93 | N525: 5 | O525: 0.0983 | P525: 43.83 | Q525: =M525*N525*(1-O525) -> 504.63641 | R525: =M525*N525*O525 -> 55.013595 | S525: =P525*N525 -> 219.15 | T525: =Q525-S525 -> 285.48641 | U525: =IFERROR(T525/Q525,0) -> 0.56572693 | V525: No | W525: Cash on Delivery
A526: ORD-00525 | B526: 45396 | C526: =YEAR(B526) -> 2024 | D526: ="Q"&ROUNDUP(MONTH(B526)/3,0) -> Q2 | E526: South | F526: Online | G526: Khaled Fathy | H526: CUST-0073 | I526: Dalia Ibrahim | J526: New / Occasional | K526: Apparel | L526: Cotton T-Shirt Pack | M526: 48.96 | N526: 3 | O526: 0.1265 | P526: 18.46 | Q526: =M526*N526*(1-O526) -> 128.29968 | R526: =M526*N526*O526 -> 18.58032 | S526: =P526*N526 -> 55.38 | T526: =Q526-S526 -> 72.91968 | U526: =IFERROR(T526/Q526,0) -> 0.56835434 | V526: No | W526: Bank Transfer
A527: ORD-00526 | B527: 45396 | C527: =YEAR(B527) -> 2024 | D527: ="Q"&ROUNDUP(MONTH(B527)/3,0) -> Q2 | E527: East | F527: Retail | G527: Yara Mostafa | H527: CUST-0001 | I527: Layla Ibrahim | J527: Key Account | K527: Apparel | L527: Denim Jeans | M527: 83.73 | N527: 2 | O527: 0.0729 | P527: 37.31 | Q527: =M527*N527*(1-O527) -> 155.25217 | R527: =M527*N527*O527 -> 12.207834 | S527: =P527*N527 -> 74.62 | T527: =Q527-S527 -> 80.632166 | U527: =IFERROR(T527/Q527,0) -> 0.51936258 | V527: Yes | W527: Bank Transfer
A528: ORD-00527 | B528: 45397 | C528: =YEAR(B528) -> 2024 | D528: ="Q"&ROUNDUP(MONTH(B528)/3,0) -> Q2 | E528: North | F528: Retail | G528: Mona Hassan | H528: CUST-0056 | I528: Mariam Farouk | J528: Standard | K528: Home & Kitchen | L528: Air Fryer | M528: 58.62 | N528: 4 | O528: 0.0968 | P528: 34.37 | Q528: =M528*N528*(1-O528) -> 211.78234 | R528: =M528*N528*O528 -> 22.697664 | S528: =P528*N528 -> 137.48 | T528: =Q528-S528 -> 74.302336 | U528: =IFERROR(T528/Q528,0) -> 0.35084293 | V528: No | W528: Cash on Delivery
A529: ORD-00528 | B529: 45397 | C529: =YEAR(B529) -> 2024 | D529: ="Q"&ROUNDUP(MONTH(B529)/3,0) -> Q2 | E529: West | F529: Online | G529: Nourhan Aly | H529: CUST-0019 | I529: Salma Hamdy | J529: Standard | K529: Apparel | L529: Cotton T-Shirt Pack | M529: 20.91 | N529: 3 | O529: 0.1202 | P529: 7.66 | Q529: =M529*N529*(1-O529) -> 55.189854 | R529: =M529*N529*O529 -> 7.540146 | S529: =P529*N529 -> 22.98 | T529: =Q529-S529 -> 32.209854 | U529: =IFERROR(T529/Q529,0) -> 0.58361912 | V529: No | W529: Cash on Delivery
A530: ORD-00529 | B530: 45397 | C530: =YEAR(B530) -> 2024 | D530: ="Q"&ROUNDUP(MONTH(B530)/3,0) -> Q2 | E530: West | F530: Retail | G530: Nourhan Aly | H530: CUST-0003 | I530: Nour Kamel | J530: Key Account | K530: Office Supplies | L530: Printer Paper (Case) | M530: 44.69 | N530: 1 | O530: 0.0416 | P530: 18.04 | Q530: =M530*N530*(1-O530) -> 42.830896 | R530: =M530*N530*O530 -> 1.859104 | S530: =P530*N530 -> 18.04 | T530: =Q530-S530 -> 24.790896 | U530: =IFERROR(T530/Q530,0) -> 0.57880872 | V530: No | W530: Bank Transfer
A531: ORD-00530 | B531: 45397 | C531: =YEAR(B531) -> 2024 | D531: ="Q"&ROUNDUP(MONTH(B531)/3,0) -> Q2 | E531: East | F531: Online | G531: Omar Said | H531: CUST-0001 | I531: Layla Ibrahim | J531: Key Account | K531: Sporting Goods | L531: Resistance Bands | M531: 154.48 | N531: 1 | O531: 0.132 | P531: 73.45 | Q531: =M531*N531*(1-O531) -> 134.08864 | R531: =M531*N531*O531 -> 20.39136 | S531: =P531*N531 -> 73.45 | T531: =Q531-S531 -> 60.63864 | U531: =IFERROR(T531/Q531,0) -> 0.45222802 | V531: No | W531: PayPal
A532: ORD-00531 | B532: 45397 | C532: =YEAR(B532) -> 2024 | D532: ="Q"&ROUNDUP(MONTH(B532)/3,0) -> Q2 | E532: North | F532: Online | G532: Tarek Aboul | H532: CUST-0012 | I532: Wael Gad | J532: Standard | K532: Sporting Goods | L532: Yoga Mat | M532: 160.3 | N532: 1 | O532: 0.0392 | P532: 72.27 | Q532: =M532*N532*(1-O532) -> 154.01624 | R532: =M532*N532*O532 -> 6.28376 | S532: =P532*N532 -> 72.27 | T532: =Q532-S532 -> 81.74624 | U532: =IFERROR(T532/Q532,0) -> 0.53076377 | V532: No | W532: PayPal
... A578: ORD-00577 | B578: 45406 | C578: =YEAR(B578) -> 2024 | D578: ="Q"&ROUNDUP(MONTH(B578)/3,0) -> Q2 | E578: East | F578: Online | G578: Yara Mostafa | H578: CUST-0017 | I578: Layla Mansour | J578: Standard | K578: Home & Kitchen | L578: Blender | M578: 106.85 | N578: 8 | O578: 0.1589 | P578: 56.28 | Q578: =M578*N578*(1-O578) -> 718.97228 | R578: =M578*N578*O578 -> 135.82772 | S578: =P578*N578 -> 450.24 | T578: =Q578-S578 -> 268.73228 | U578: =IFERROR(T578/Q578,0) -> 0.3737728 | V578: No | W578: Bank Transfer
A579: ORD-00578 | B579: 45406 | C579: =YEAR(B579) -> 2024 | D579: ="Q"&ROUNDUP(MONTH(B579)/3,0) -> Q2 | E579: South | F579: Wholesale | G579: Sara Adel | H579: CUST-0081 | I579: Reem Abdallah | J579: New / Occasional | K579: Office Supplies | L579: Printer Paper (Case) | M579: 212.67 | N579: 48 | P579: 116.75 | Q579: =M579*N579*(1-O579) -> 10208.16 | R579: =M579*N579*O579 -> 0 | S579: =P579*N579 -> 5604 | T579: =Q579-S579 -> 4604.16 | U579: =IFERROR(T579/Q579,0) -> 0.45102741 | V579: No | W579: Credit Card
A580: ORD-00579 | B580: 45406 | C580: =YEAR(B580) -> 2024 | D580: ="Q"&ROUNDUP(MONTH(B580)/3,0) -> Q2 | E580: Central | F580: Online | G580: Laila Younis | H580: CUST-0012 | I580: Wael Gad | J580: Standard | K580: Office Supplies | L580: Ergonomic Chair | M580: 154.07 | N580: 1 | O580: 0.121 | P580: 77.54 | Q580: =M580*N580*(1-O580) -> 135.42753 | R580: =M580*N580*O580 -> 18.64247 | S580: =P580*N580 -> 77.54 | T580: =Q580-S580 -> 57.88753 | U580: =IFERROR(T580/Q580,0) -> 0.42744285 | V580: No | W580: PayPal
A581: ORD-00580 | B581: 45406 | C581: =YEAR(B581) -> 2024 | D581: ="Q"&ROUNDUP(MONTH(B581)/3,0) -> Q2 | E581: West | F581: Retail | G581: Nourhan Aly | H581: CUST-0010 | I581: Reem Farouk | J581: Key Account | K581: Office Supplies | L581: Standing Desk | M581: 282.86 | N581: 3 | O581: 0.0865 | P581: 144.5 | Q581: =M581*N581*(1-O581) -> 775.17783 | R581: =M581*N581*O581 -> 73.40217 | S581: =P581*N581 -> 433.5 | T581: =Q581-S581 -> 341.67783 | U581: =IFERROR(T581/Q581,0) -> 0.44077348 | V581: No | W581: PayPal
A582: ORD-00581 | B582: 45406 | C582: =YEAR(B582) -> 2024 | D582: ="Q"&ROUNDUP(MONTH(B582)/3,0) -> Q2 | E582: South | F582: Online | G582: Khaled Fathy | H582: CUST-0001 | I582: Layla Ibrahim | J582: Key Account | K582: Office Supplies | L582: LED Desk Lamp | M582: 13.65 | N582: 1 | O582: 0.1738 | P582: 6.64 | Q582: =M582*N582*(1-O582) -> 11.27763 | R582: =M582*N582*O582 -> 2.37237 | S582: =P582*N582 -> 6.64 | T582: =Q582-S582 -> 4.63763 | U582: =IFERROR(T582/Q582,0) -> 0.41122381 | V582: No | W582: PayPal
A583: ORD-00582 | B583: 45406 | C583: =YEAR(B583) -> 2024 | D583: ="Q"&ROUNDUP(MONTH(B583)/3,0) -> Q2 | E583: Central | F583: Online | G583: Dina Magdy | H583: CUST-0007 | I583: Hassan Naguib | J583: Key Account | K583: Office Supplies | L583: Desk Organizer | M583: 163.87 | N583: 3 | O583: 0.125 | P583: 81.05 | Q583: =M583*N583*(1-O583) -> 430.15875 | R583: =M583*N583*O583 -> 61.45125 | S583: =P583*N583 -> 243.15 | T583: =Q583-S583 -> 187.00875 | U583: =IFERROR(T583/Q583,0) -> 0.43474357 | V583: Yes | W583: PayPal
A584: ORD-00583 | B584: 45406 | C584: =YEAR(B584) -> 2024 | D584: ="Q"&ROUNDUP(MONTH(B584)/3,0) -> Q2 | E584: South | F584: Online | G584: Khaled Fathy | H584: CUST-0007 | I584: Hassan Naguib | J584: Key Account | K584: Apparel | L584: Cotton T-Shirt Pack | M584: 69.28 | N584: 1 | O584: 0.1137 | P584: 28.37 | Q584: =M584*N584*(1-O584) -> 61.402864 | R584: =M584*N584*O584 -> 7.877136 | S584: =P584*N584 -> 28.37 | T584: =Q584-S584 -> 33.032864 | U584: =IFERROR(T584/Q584,0) -> 0.53796943 | V584: No | W584: PayPal
A585: ORD-00584 | B585: 45407 | C585: =YEAR(B585) -> 2024 | D585: ="Q"&ROUNDUP(MONTH(B585)/3,0) -> Q2 | E585: South | F585: Online | G585: Khaled Fathy | H585: CUST-0011 | I585: Nour Aziz | J585: Standard | K585: Sporting Goods | L585: Adjustable Dumbbells | M585: 115.62 | N585: 1 | O585: 0.1029 | P585: 61.24 | Q585: =M585*N585*(1-O585) -> 103.7227 | R585: =M585*N585*O585 -> 11.897298 | S585: =P585*N585 -> 61.24 | T585: =Q585-S585 -> 42.482702 | U585: =IFERROR(T585/Q585,0) -> 0.40957959 | V585: Yes | W585: Bank Transfer
A586: ORD-00585 | B586: 45407 | C586: =YEAR(B586) -> 2024 | D586: ="Q"&ROUNDUP(MONTH(B586)/3,0) -> Q2 | E586: West | F586: Retail | G586: Nourhan Aly | H586: CUST-0157 | I586: Sami Fahmy | J586: New / Occasional | K586: Apparel | L586: Leather Belt | M586: 123.53 | N586: 3 | O586: 0.0827 | P586: 59.22 | Q586: =M586*N586*(1-O586) -> 339.94221 | R586: =M586*N586*O586 -> 30.647793 | S586: =P586*N586 -> 177.66 | T586: =Q586-S586 -> 162.28221 | U586: =IFERROR(T586/Q586,0) -> 0.47738175 | V586: No | W586: Bank Transfer
A587: ORD-00586 | B587: 45407 | C587: =YEAR(B587) -> 2024 | D587: ="Q"&ROUNDUP(MONTH(B587)/3,0) -> Q2 | E587: West | F587: Online | G587: Hossam Zaki | H587: CUST-0008 | I587: Nour Ibrahim | J587: Key Account | K587: Home & Kitchen | L587: Coffee Maker | M587: 48.62 | N587: 1 | O587: 0.0732 | P587: 25.89 | Q587: =M587*N587*(1-O587) -> 45.061016 | R587: =M587*N587*O587 -> 3.558984 | S587: =P587*N587 -> 25.89 | T587: =Q587-S587 -> 19.171016 | U587: =IFERROR(T587/Q587,0) -> 0.42544571 | V587: No | W587: Bank Transfer
A588: ORD-00587 | B588: 45407 | C588: =YEAR(B588) -> 2024 | D588: ="Q"&ROUNDUP(MONTH(B588)/3,0) -> Q2 | E588: West | F588: Wholesale | G588: Nourhan Aly | H588: CUST-0014 | I588: Rania El-Masry | J588: Standard | K588: Office Supplies | L588: Standing Desk | M588: 103.88 | N588: 25 | O588: 0.0267 | P588: 50.24 | Q588: =M588*N588*(1-O588) -> 2527.6601 | R588: =M588*N588*O588 -> 69.3399 | S588: =P588*N588 -> 1256 | T588: =Q588-S588 -> 1271.6601 | U588: =IFERROR(T588/Q588,0) -> 0.50309775 | V588: No | W588: PayPal
A589: ORD-00588 | B589: 45407 | C589: =YEAR(B589) -> 2024 | D589: ="Q"&ROUNDUP(MONTH(B589)/3,0) -> Q2 | E589: West | F589: Online | G589: Hossam Zaki | H589: CUST-0014 | I589: Rania El-Masry | J589: Standard | K589: Apparel | L589: Running Shoes | M589: 46.75 | N589: 1 | O589: 0.1281 | P589: 16.97 | Q589: =M589*N589*(1-O589) -> 40.761325 | R589: =M589*N589*O589 -> 5.988675 | S589: =P589*N589 -> 16.97 | T589: =Q589-S589 -> 23.791325 | U589: =IFERROR(T589/Q589,0) -> 0.58367399 | V589: No | W589: PayPal
A590: ORD-00589 | B590: 45408 | C590: =YEAR(B590) -> 2024 | D590: ="Q"&ROUNDUP(MONTH(B590)/3,0) -> Q2 | E590: North | F590: Online | G590: Mona Hassan | H590: CUST-0008 | I590: Nour Ibrahim | J590: Key Account | K590: Sporting Goods | L590: Yoga Mat | M590: 62.92 | N590: 5 | O590: 0.1567 | P590: 33.66 | Q590: =M590*N590*(1-O590) -> 265.30218 | R590: =M590*N590*O590 -> 49.29782 | S590: =P590*N590 -> 168.3 | T590: =Q590-S590 -> 97.00218 | U590: =IFERROR(T590/Q590,0) -> 0.36562903 | V590: No | W590: Bank Transfer
A591: ORD-00590 | B591: 45408 | C591: =YEAR(B591) -> 2024 | D591: ="Q"&ROUNDUP(MONTH(B591)/3,0) -> Q2 | E591: North | F591: Online | G591: Tarek Aboul | H591: CUST-0134 | I591: Hala Mansour | J591: New / Occasional | K591: Home & Kitchen | L591: Blender | M591: 65.36 | N591: 1 | O591: 0.0524 | P591: 35.6 | Q591: =M591*N591*(1-O591) -> 61.935136 | R591: =M591*N591*O591 -> 3.424864 | S591: =P591*N591 -> 35.6 | T591: =Q591-S591 -> 26.335136 | U591: =IFERROR(T591/Q591,0) -> 0.4252051 | V591: No | W591: Credit Card
...

Sheet Analysis_Data
A1: Company Totals
A2: Total Revenue | B2: =SUM(Sales_Transactions!$Q$2:$Q$4411) -> 1945626.1
A3: Total Net Profit | B3: =SUM(Sales_Transactions!$T$2:$T$4411) -> 744281.38
A4: Overall Margin % | B4: =B3/B2 -> 0.38254081
A5: Total Orders | B5: =COUNTA(Sales_Transactions!$H$2:$H$4411) -> 4410
A6: Company Return Rate | B6: =COUNTIF(Sales_Transactions!$V$2:$V$4411,"Yes")/B5 -> 0.079591837
A9: Problem 1 — Customer Revenue Concentration (Top 20 of 180 Customers)
A10: Rank | B10: Customer_ID | C10: Customer_Name | D10: Segment | E10: Revenue | F10: Cumulative Revenue | G10: Cumulative %
A11: 1 | B11: CUST-0002 | C11: Sami Sherif | D11: Key Account | E11: =SUMIF(Sales_Transactions!$H$2:$H$4411,B11,Sales_Transactions!$Q$2:$Q$4411) -> 94608.859 | F11: =E11 -> 94608.859 | G11: =F11/$B$2 -> 0.048626435
A12: 2 | B12: CUST-0003 | C12: Nour Kamel | D12: Key Account | E12: =SUMIF(Sales_Transactions!$H$2:$H$4411,B12,Sales_Transactions!$Q$2:$Q$4411) -> 90463.351 | F12: =F11+E12 -> 185072.21 | G12: =F12/$B$2 -> 0.095122188
A13: 3 | B13: CUST-0004 | C13: Layla Mansour | D13: Key Account | E13: =SUMIF(Sales_Transactions!$H$2:$H$4411,B13,Sales_Transactions!$Q$2:$Q$4411) -> 86586.325 | F13: =F12+E13 -> 271658.54 | G13: =F13/$B$2 -> 0.13962525
A14: 4 | B14: CUST-0005 | C14: Wael Farouk | D14: Key Account | E14: =SUMIF(Sales_Transactions!$H$2:$H$4411,B14,Sales_Transactions!$Q$2:$Q$4411) -> 78959.784 | F14: =F13+E14 -> 350618.32 | G14: =F14/$B$2 -> 0.18020848
A15: 5 | B15: CUST-0001 | C15: Layla Ibrahim | D15: Key Account | E15: =SUMIF(Sales_Transactions!$H$2:$H$4411,B15,Sales_Transactions!$Q$2:$Q$4411) -> 76555.401 | F15: =F14+E15 -> 427173.72 | G15: =F15/$B$2 -> 0.21955592
A16: 6 | B16: CUST-0006 | C16: Mona Ibrahim | D16: Key Account | E16: =SUMIF(Sales_Transactions!$H$2:$H$4411,B16,Sales_Transactions!$Q$2:$Q$4411) -> 52236.529 | F16: =F15+E16 -> 479410.25 | G16: =F16/$B$2 -> 0.2464041
A17: 7 | B17: CUST-0007 | C17: Hassan Naguib | D17: Key Account | E17: =SUMIF(Sales_Transactions!$H$2:$H$4411,B17,Sales_Transactions!$Q$2:$Q$4411) -> 50640.551 | F17: =F16+E17 -> 530050.8 | G17: =F17/$B$2 -> 0.272432
A18: 8 | B18: CUST-0009 | C18: Reem Naguib | D18: Key Account | E18: =SUMIF(Sales_Transactions!$H$2:$H$4411,B18,Sales_Transactions!$Q$2:$Q$4411) -> 50384.048 | F18: =F17+E18 -> 580434.85 | G18: =F18/$B$2 -> 0.29832806
A19: 9 | B19: CUST-0008 | C19: Nour Ibrahim | D19: Key Account | E19: =SUMIF(Sales_Transactions!$H$2:$H$4411,B19,Sales_Transactions!$Q$2:$Q$4411) -> 38400.601 | F19: =F18+E19 -> 618835.45 | G19: =F19/$B$2 -> 0.31806494
A20: 10 | B20: CUST-0010 | C20: Reem Farouk | D20: Key Account | E20: =SUMIF(Sales_Transactions!$H$2:$H$4411,B20,Sales_Transactions!$Q$2:$Q$4411) -> 34718.372 | F20: =F19+E20 -> 653553.82 | G20: =F20/$B$2 -> 0.33590926
A21: 11 | B21: CUST-0016 | C21: Karim El-Masry | D21: Standard | E21: =SUMIF(Sales_Transactions!$H$2:$H$4411,B21,Sales_Transactions!$Q$2:$Q$4411) -> 33521.242 | F21: =F20+E21 -> 687075.06 | G21: =F21/$B$2 -> 0.35313829
A22: 12 | B22: CUST-0019 | C22: Salma Hamdy | D22: Standard | E22: =SUMIF(Sales_Transactions!$H$2:$H$4411,B22,Sales_Transactions!$Q$2:$Q$4411) -> 29934.677 | F22: =F21+E22 -> 717009.74 | G22: =F22/$B$2 -> 0.36852392
A23: 13 | B23: CUST-0013 | C23: Ali Abdallah | D23: Standard | E23: =SUMIF(Sales_Transactions!$H$2:$H$4411,B23,Sales_Transactions!$Q$2:$Q$4411) -> 29165.326 | F23: =F22+E23 -> 746175.07 | G23: =F23/$B$2 -> 0.38351412
... A30: 20 | B30: CUST-0041 | C30: Nour El-Sayed | D30: Standard | E30: =SUMIF(Sales_Transactions!$H$2:$H$4411,B30,Sales_Transactions!$Q$2:$Q$4411) -> 24345.432 | F30: =F29+E30 -> 926708.6 | G30: =F30/$B$2 -> 0.47630355
B31: OTHER | C31: All Other Customers (160) | D31: Mixed | E31: =$B$2-F30 -> 1018917.5 | F31: =$B$2 -> 1945626.1 | G31: 1
A34: Problem 2 — Monthly Discount & Margin Trend
A35: Month | B35: Revenue | C35: Discount Amount | D35: Net Profit | E35: Avg Discount % | F35: Margin %
A36: 45292 | B36: =SUMIFS(Sales_Transactions!$Q$2:$Q$4411,Sales_Transactions!$B$2:$B$4411,">="&A36,Sales_Transactions!$B$2:$B$4411,"<"&EDATE(A36,1)) -> 86466.817 | C36: =SUMIFS(Sales_Transactions!$R$2:$R$4411,Sales_Transactions!$B$2:$B$4411,">="&A36,Sales_Transactions!$B$2:$B$4411,"<"&EDATE(A36,1)) -> 4891.1532 | D36: =SUMIFS(Sales_Transactions!$T$2:$T$4411,Sales_Transactions!$B$2:$B$4411,">="&A36,Sales_Transactions!$B$2:$B$4411,"<"&EDATE(A36,1)) -> 37713.057 | E36: =C36/(B36+C36) -> 0.05353833 | F36: =IFERROR(D36/B36,0) -> 0.43615641
A37: =EDATE(A36,1) -> 45323 | B37: =SUMIFS(Sales_Transactions!$Q$2:$Q$4411,Sales_Transactions!$B$2:$B$4411,">="&A37,Sales_Transactions!$B$2:$B$4411,"<"&EDATE(A37,1)) -> 60468.182 | C37: =SUMIFS(Sales_Transactions!$R$2:$R$4411,Sales_Transactions!$B$2:$B$4411,">="&A37,Sales_Transactions!$B$2:$B$4411,"<"&EDATE(A37,1)) -> 5232.8884 | D37: =SUMIFS(Sales_Transactions!$T$2:$T$4411,Sales_Transactions!$B$2:$B$4411,">="&A37,Sales_Transactions!$B$2:$B$4411,"<"&EDATE(A37,1)) -> 24836.102 | E37: =C37/(B37+C37) -> 0.079646928 | F37: =IFERROR(D37/B37,0) -> 0.41073009
A38: =EDATE(A37,1) -> 45352 | B38: =SUMIFS(Sales_Transactions!$Q$2:$Q$4411,Sales_Transactions!$B$2:$B$4411,">="&A38,Sales_Transactions!$B$2:$B$4411,"<"&EDATE(A38,1)) -> 74031.7 | C38: =SUMIFS(Sales_Transactions!$R$2:$R$4411,Sales_Transactions!$B$2:$B$4411,">="&A38,Sales_Transactions!$B$2:$B$4411,"<"&EDATE(A38,1)) -> 6370.6105 | D38: =SUMIFS(Sales_Transactions!$T$2:$T$4411,Sales_Transactions!$B$2:$B$4411,">="&A38,Sales_Transactions!$B$2:$B$4411,"<"&EDATE(A38,1)) -> 31142.15 | E38: =C38/(B38+C38) -> 0.079234172 | F38: =IFERROR(D38/B38,0) -> 0.42065966
A39: =EDATE(A38,1) -> 45383 | B39: =SUMIFS(Sales_Transactions!$Q$2:$Q$4411,Sales_Transactions!$B$2:$B$4411,">="&A39,Sales_Transactions!$B$2:$B$4411,"<"&EDATE(A39,1)) -> 94800.131 | C39: =SUMIFS(Sales_Transactions!$R$2:$R$4411,Sales_Transactions!$B$2:$B$4411,">="&A39,Sales_Transactions!$B$2:$B$4411,"<"&EDATE(A39,1)) -> 6807.919 | D39: =SUMIFS(Sales_Transactions!$T$2:$T$4411,Sales_Transactions!$B$2:$B$4411,">="&A39,Sales_Transactions!$B$2:$B$4411,"<"&EDATE(A39,1)) -> 40112.431 | E39: =C39/(B39+C39) -> 0.067001768 | F39: =IFERROR(D39/B39,0) -> 0.42312632
A40: =EDATE(A39,1) -> 45413 | B40: =SUMIFS(Sales_Transactions!$Q$2:$Q$4411,Sales_Transactions!$B$2:$B$4411,">="&A40,Sales_Transactions!$B$2:$B$4411,"<"&EDATE(A40,1)) -> 62752.658 | C40: =SUMIFS(Sales_Transactions!$R$2:$R$4411,Sales_Transactions!$B$2:$B$4411,">="&A40,Sales_Transactions!$B$2:$B$4411,"<"&EDATE(A40,1)) -> 5358.4724 | D40: =SUMIFS(Sales_Transactions!$T$2:$T$4411,Sales_Transactions!$B$2:$B$4411,">="&A40,Sales_Transactions!$B$2:$B$4411,"<"&EDATE(A40,1)) -> 25418.158 | E40: =C40/(B40+C40) -> 0.078672493 | F40: =IFERROR(D40/B40,0) -> 0.40505309
A41: =EDATE(A40,1) -> 45444 | B41: =SUMIFS(Sales_Transactions!$Q$2:$Q$4411,Sales_Transactions!$B$2:$B$4411,">="&A41,Sales_Transactions!$B$2:$B$4411,"<"&EDATE(A41,1)) -> 75030.305 | C41: =SUMIFS(Sales_Transactions!$R$2:$R$4411,Sales_Transactions!$B$2:$B$4411,">="&A41,Sales_Transactions!$B$2:$B$4411,"<"&EDATE(A41,1)) -> 8497.2354 | D41: =SUMIFS(Sales_Transactions!$T$2:$T$4411,Sales_Transactions!$B$2:$B$4411,">="&A41,Sales_Transactions!$B$2:$B$4411,"<"&EDATE(A41,1)) -> 30145.795 | E41: =C41/(B41+C41) -> 0.10172975 | F41: =IFERROR(D41/B41,0) -> 0.40178158
A42: =EDATE(A41,1) -> 45474 | B42: =SUMIFS(Sales_Transactions!$Q$2:$Q$4411,Sales_Transactions!$B$2:$B$4411,">="&A42,Sales_Transactions!$B$2:$B$4411,"<"&EDATE(A42,1)) -> 63619.357 | C42: =SUMIFS(Sales_Transactions!$R$2:$R$4411,Sales_Transactions!$B$2:$B$4411,">="&A42,Sales_Transactions!$B$2:$B$4411,"<"&EDATE(A42,1)) -> 7188.3033 | D42: =SUMIFS(Sales_Transactions!$T$2:$T$4411,Sales_Transactions!$B$2:$B$4411,">="&A42,Sales_Transactions!$B$2:$B$4411,"<"&EDATE(A42,1)) -> 25231.877 | E42: =C42/(B42+C42) -> 0.10151872 | F42: =IFERROR(D42/B42,0) -> 0.39660691
A43: =EDATE(A42,1) -> 45505 | B43: =SUMIFS(Sales_Transactions!$Q$2:$Q$4411,Sales_Transactions!$B$2:$B$4411,">="&A43,Sales_Transactions!$B$2:$B$4411,"<"&EDATE(A43,1)) -> 74740.35 | C43: =SUMIFS(Sales_Transactions!$R$2:$R$4411,Sales_Transactions!$B$2:$B$4411,">="&A43,Sales_Transactions!$B$2:$B$4411,"<"&EDATE(A43,1)) -> 9449.56 | D43: =SUMIFS(Sales_Transactions!$T$2:$T$4411,Sales_Transactions!$B$2:$B$4411,">="&A43,Sales_Transactions!$B$2:$B$4411,"<"&EDATE(A43,1)) -> 29307.34 | E43: =C43/(B43+C43) -> 0.112241 | F43: =IFERROR(D43/B43,0) -> 0.39212206
A44: =EDATE(A43,1) -> 45536 | B44: =SUMIFS(Sales_Transactions!$Q$2:$Q$4411,Sales_Transactions!$B$2:$B$4411,">="&A44,Sales_Transactions!$B$2:$B$4411,"<"&EDATE(A44,1)) -> 62334.823 | C44: =SUMIFS(Sales_Transactions!$R$2:$R$4411,Sales_Transactions!$B$2:$B$4411,">="&A44,Sales_Transactions!$B$2:$B$4411,"<"&EDATE(A44,1)) -> 8194.0966 | D44: =SUMIFS(Sales_Transactions!$T$2:$T$4411,Sales_Transactions!$B$2:$B$4411,">="&A44,Sales_Transactions!$B$2:$B$4411,"<"&EDATE(A44,1)) -> 25746.663 | E44: =C44/(B44+C44) -> 0.11618066 | F44: =IFERROR(D44/B44,0) -> 0.4130382
A45: =EDATE(A44,1) -> 45566 | B45: =SUMIFS(Sales_Transactions!$Q$2:$Q$4411,Sales_Transactions!$B$2:$B$4411,">="&A45,Sales_Transactions!$B$2:$B$4411,"<"&EDATE(A45,1)) -> 71834.66 | C45: =SUMIFS(Sales_Transactions!$R$2:$R$4411,Sales_Transactions!$B$2:$B$4411,">="&A45,Sales_Transactions!$B$2:$B$4411,"<"&EDATE(A45,1)) -> 9697.8901 | D45: =SUMIFS(Sales_Transactions!$T$2:$T$4411,Sales_Transactions!$B$2:$B$4411,">="&A45,Sales_Transactions!$B$2:$B$4411,"<"&EDATE(A45,1)) -> 27971.43 | E45: =C45/(B45+C45) -> 0.11894501 | F45: =IFERROR(D45/B45,0) -> 0.38938626
A46: =EDATE(A45,1) -> 45597 | B46: =SUMIFS(Sales_Transactions!$Q$2:$Q$4411,Sales_Transactions!$B$2:$B$4411,">="&A46,Sales_Transactions!$B$2:$B$4411,"<"&EDATE(A46,1)) -> 91333.669 | C46: =SUMIFS(Sales_Transactions!$R$2:$R$4411,Sales_Transactions!$B$2:$B$4411,">="&A46,Sales_Transactions!$B$2:$B$4411,"<"&EDATE(A46,1)) -> 15466.271 | D46: =SUMIFS(Sales_Transactions!$T$2:$T$4411,Sales_Transactions!$B$2:$B$4411,">="&A46,Sales_Transactions!$B$2:$B$4411,"<"&EDATE(A46,1)) -> 35644.269 | E46: =C46/(B46+C46) -> 0.14481536 | F46: =IFERROR(D46/B46,0) -> 0.39026428
A47: =EDATE(A46,1) -> 45627 | B47: =SUMIFS(Sales_Transactions!$Q$2:$Q$4411,Sales_Transactions!$B$2:$B$4411,">="&A47,Sales_Transactions!$B$2:$B$4411,"<"&EDATE(A47,1)) -> 114014.76 | C47: =SUMIFS(Sales_Transactions!$R$2:$R$4411,Sales_Transactions!$B$2:$B$4411,">="&A47,Sales_Transactions!$B$2:$B$4411,"<"&EDATE(A47,1)) -> 17504.913 | D47: =SUMIFS(Sales_Transactions!$T$2:$T$4411,Sales_Transactions!$B$2:$B$4411,">="&A47,Sales_Transactions!$B$2:$B$4411,"<"&EDATE(A47,1)) -> 45107.457 | E47: =C47/(B47+C47) -> 0.1330973 | F47: =IFERROR(D47/B47,0) -> 0.39562823
A48: =EDATE(A47,1) -> 45658 | B48: =SUMIFS(Sales_Transactions!$Q$2:$Q$4411,Sales_Transactions!$B$2:$B$4411,">="&A48,Sales_Transactions!$B$2:$B$4411,"<"&EDATE(A48,1)) -> 85492.521 | C48: =SUMIFS(Sales_Transactions!$R$2:$R$4411,Sales_Transactions!$B$2:$B$4411,">="&A48,Sales_Transactions!$B$2:$B$4411,"<"&EDATE(A48,1)) -> 11899.179 | D48: =SUMIFS(Sales_Transactions!$T$2:$T$4411,Sales_Transactions!$B$2:$B$4411,">="&A48,Sales_Transactions!$B$2:$B$4411,"<"&EDATE(A48,1)) -> 34617.821 | E48: =C48/(B48+C48) -> 0.12217857 | F48: =IFERROR(D48/B48,0) -> 0.40492222
... A59: =EDATE(A58,1) -> 45992 | B59: =SUMIFS(Sales_Transactions!$Q$2:$Q$4411,Sales_Transactions!$B$2:$B$4411,">="&A59,Sales_Transactions!$B$2:$B$4411,"<"&EDATE(A59,1)) -> 127567.88 | C59: =SUMIFS(Sales_Transactions!$R$2:$R$4411,Sales_Transactions!$B$2:$B$4411,">="&A59,Sales_Transactions!$B$2:$B$4411,"<"&EDATE(A59,1)) -> 33406.296 | D59: =SUMIFS(Sales_Transactions!$T$2:$T$4411,Sales_Transactions!$B$2:$B$4411,">="&A59,Sales_Transactions!$B$2:$B$4411,"<"&EDATE(A59,1)) -> 43150.704 | E59: =C59/(B59+C59) -> 0.2075258 | F59: =IFERROR(D59/B59,0) -> 0.3382568
A62: Problem 3 — Regional Revenue Trend by Month
A63: Month | B63: North | C63: East | D63: West | E63: Central | F63: South
A64: =A36 -> 45292 | B64: =SUMIFS(Sales_Transactions!$Q$2:$Q$4411,Sales_Transactions!$E$2:$E$4411,"North",Sales_Transactions!$B$2:$B$4411,">="&A64,Sales_Transactions!$B$2:$B$4411,"<"&EDATE(A64,1)) -> 25099.051 | C64: =SUMIFS(Sales_Transactions!$Q$2:$Q$4411,Sales_Transactions!$E$2:$E$4411,"East",Sales_Transactions!$B$2:$B$4411,">="&A64,Sales_Transactions!$B$2:$B$4411,"<"&EDATE(A64,1)) -> 11030.638 | D64: =SUMIFS(Sales_Transactions!$Q$2:$Q$4411,Sales_Transactions!$E$2:$E$4411,"West",Sales_Transactions!$B$2:$B$4411,">="&A64,Sales_Transactions!$B$2:$B$4411,"<"&EDATE(A64,1)) -> 9991.3193 | E64: =SUMIFS(Sales_Transactions!$Q$2:$Q$4411,Sales_Transactions!$E$2:$E$4411,"Central",Sales_Transactions!$B$2:$B$4411,">="&A64,Sales_Transactions!$B$2:$B$4411,"<"&EDATE(A64,1)) -> 15018.334 | F64: =SUMIFS(Sales_Transactions!$Q$2:$Q$4411,Sales_Transactions!$E$2:$E$4411,"South",Sales_Transactions!$B$2:$B$4411,">="&A64,Sales_Transactions!$B$2:$B$4411,"<"&EDATE(A64,1)) -> 25327.474
A65: =A37 -> 45323 | B65: =SUMIFS(Sales_Transactions!$Q$2:$Q$4411,Sales_Transactions!$E$2:$E$4411,"North",Sales_Transactions!$B$2:$B$4411,">="&A65,Sales_Transactions!$B$2:$B$4411,"<"&EDATE(A65,1)) -> 18718.059 | C65: =SUMIFS(Sales_Transactions!$Q$2:$Q$4411,Sales_Transactions!$E$2:$E$4411,"East",Sales_Transactions!$B$2:$B$4411,">="&A65,Sales_Transactions!$B$2:$B$4411,"<"&EDATE(A65,1)) -> 3230.7889 | D65: =SUMIFS(Sales_Transactions!$Q$2:$Q$4411,Sales_Transactions!$E$2:$E$4411,"West",Sales_Transactions!$B$2:$B$4411,">="&A65,Sales_Transactions!$B$2:$B$4411,"<"&EDATE(A65,1)) -> 11102.44 | E65: =SUMIFS(Sales_Transactions!$Q$2:$Q$4411,Sales_Transactions!$E$2:$E$4411,"Central",Sales_Transactions!$B$2:$B$4411,">="&A65,Sales_Transactions!$B$2:$B$4411,"<"&EDATE(A65,1)) -> 11541.606 | F65: =SUMIFS(Sales_Transactions!$Q$2:$Q$4411,Sales_Transactions!$E$2:$E$4411,"South",Sales_Transactions!$B$2:$B$4411,">="&A65,Sales_Transactions!$B$2:$B$4411,"<"&EDATE(A65,1)) -> 15875.288
A66: =A38 -> 45352 | B66: =SUMIFS(Sales_Transactions!$Q$2:$Q$4411,Sales_Transactions!$E$2:$E$4411,"North",Sales_Transactions!$B$2:$B$4411,">="&A66,Sales_Transactions!$B$2:$B$4411,"<"&EDATE(A66,1)) -> 15675.458 | C66: =SUMIFS(Sales_Transactions!$Q$2:$Q$4411,Sales_Transactions!$E$2:$E$4411,"East",Sales_Transactions!$B$2:$B$4411,">="&A66,Sales_Transactions!$B$2:$B$4411,"<"&EDATE(A66,1)) -> 17306.353 | D66: =SUMIFS(Sales_Transactions!$Q$2:$Q$4411,Sales_Transactions!$E$2:$E$4411,"West",Sales_Transactions!$B$2:$B$4411,">="&A66,Sales_Transactions!$B$2:$B$4411,"<"&EDATE(A66,1)) -> 14144.539 | E66: =SUMIFS(Sales_Transactions!$Q$2:$Q$4411,Sales_Transactions!$E$2:$E$4411,"Central",Sales_Transactions!$B$2:$B$4411,">="&A66,Sales_Transactions!$B$2:$B$4411,"<"&EDATE(A66,1)) -> 10256.537 | F66: =SUMIFS(Sales_Transactions!$Q$2:$Q$4411,Sales_Transactions!$E$2:$E$4411,"South",Sales_Transactions!$B$2:$B$4411,">="&A66,Sales_Transactions!$B$2:$B$4411,"<"&EDATE(A66,1)) -> 16648.812
A67: =A39 -> 45383 | B67: =SUMIFS(Sales_Transactions!$Q$2:$Q$4411,Sales_Transactions!$E$2:$E$4411,"North",Sales_Transactions!$B$2:$B$4411,">="&A67,Sales_Transactions!$B$2:$B$4411,"<"&EDATE(A67,1)) -> 14033.304 | C67: =SUMIFS(Sales_Transactions!$Q$2:$Q$4411,Sales_Transactions!$E$2:$E$4411,"East",Sales_Transactions!$B$2:$B$4411,">="&A67,Sales_Transactions!$B$2:$B$4411,"<"&EDATE(A67,1)) -> 14535.441 | D67: =SUMIFS(Sales_Transactions!$Q$2:$Q$4411,Sales_Transactions!$E$2:$E$4411,"West",Sales_Transactions!$B$2:$B$4411,">="&A67,Sales_Transactions!$B$2:$B$4411,"<"&EDATE(A67,1)) -> 23965.254 | E67: =SUMIFS(Sales_Transactions!$Q$2:$Q$4411,Sales_Transactions!$E$2:$E$4411,"Central",Sales_Transactions!$B$2:$B$4411,">="&A67,Sales_Transactions!$B$2:$B$4411,"<"&EDATE(A67,1)) -> 7110.3479 | F67: =SUMIFS(Sales_Transactions!$Q$2:$Q$4411,Sales_Transactions!$E$2:$E$4411,"South",Sales_Transactions!$B$2:$B$4411,">="&A67,Sales_Transactions!$B$2:$B$4411,"<"&EDATE(A67,1)) -> 35155.784
A68: =A40 -> 45413 | B68: =SUMIFS(Sales_Transactions!$Q$2:$Q$4411,Sales_Transactions!$E$2:$E$4411,"North",Sales_Transactions!$B$2:$B$4411,">="&A68,Sales_Transactions!$B$2:$B$4411,"<"&EDATE(A68,1)) -> 19331.008 | C68: =SUMIFS(Sales_Transactions!$Q$2:$Q$4411,Sales_Transactions!$E$2:$E$4411,"East",Sales_Transactions!$B$2:$B$4411,">="&A68,Sales_Transactions!$B$2:$B$4411,"<"&EDATE(A68,1)) -> 7416.6101 | D68: =SUMIFS(Sales_Transactions!$Q$2:$Q$4411,Sales_Transactions!$E$2:$E$4411,"West",Sales_Transactions!$B$2:$B$4411,">="&A68,Sales_Transactions!$B$2:$B$4411,"<"&EDATE(A68,1)) -> 16303.196 | E68: =SUMIFS(Sales_Transactions!$Q$2:$Q$4411,Sales_Transactions!$E$2:$E$4411,"Central",Sales_Transactions!$B$2:$B$4411,">="&A68,Sales_Transactions!$B$2:$B$4411,"<"&EDATE(A68,1)) -> 5770.3626 | F68: =SUMIFS(Sales_Transactions!$Q$2:$Q$4411,Sales_Transactions!$E$2:$E$4411,"South",Sales_Transactions!$B$2:$B$4411,">="&A68,Sales_Transactions!$B$2:$B$4411,"<"&EDATE(A68,1)) -> 13931.481
A69: =A41 -> 45444 | B69: =SUMIFS(Sales_Transactions!$Q$2:$Q$4411,Sales_Transactions!$E$2:$E$4411,"North",Sales_Transactions!$B$2:$B$4411,">="&A69,Sales_Transactions!$B$2:$B$4411,"<"&EDATE(A69,1)) -> 11761.214 | C69: =SUMIFS(Sales_Transactions!$Q$2:$Q$4411,Sales_Transactions!$E$2:$E$4411,"East",Sales_Transactions!$B$2:$B$4411,">="&A69,Sales_Transactions!$B$2:$B$4411,"<"&EDATE(A69,1)) -> 11424.574 | D69: =SUMIFS(Sales_Transactions!$Q$2:$Q$4411,Sales_Transactions!$E$2:$E$4411,"West",Sales_Transactions!$B$2:$B$4411,">="&A69,Sales_Transactions!$B$2:$B$4411,"<"&EDATE(A69,1)) -> 19720.417 | E69: =SUMIFS(Sales_Transactions!$Q$2:$Q$4411,Sales_Transactions!$E$2:$E$4411,"Central",Sales_Transactions!$B$2:$B$4411,">="&A69,Sales_Transactions!$B$2:$B$4411,"<"&EDATE(A69,1)) -> 8541.0423 | F69: =SUMIFS(Sales_Transactions!$Q$2:$Q$4411,Sales_Transactions!$E$2:$E$4411,"South",Sales_Transactions!$B$2:$B$4411,">="&A69,Sales_Transactions!$B$2:$B$4411,"<"&EDATE(A69,1)) -> 23583.058
A70: =A42 -> 45474 | B70: =SUMIFS(Sales_Transactions!$Q$2:$Q$4411,Sales_Transactions!$E$2:$E$4411,"North",Sales_Transactions!$B$2:$B$4411,">="&A70,Sales_Transactions!$B$2:$B$4411,"<"&EDATE(A70,1)) -> 15007.808 | C70: =SUMIFS(Sales_Transactions!$Q$2:$Q$4411,Sales_Transactions!$E$2:$E$4411,"East",Sales_Transactions!$B$2:$B$4411,">="&A70,Sales_Transactions!$B$2:$B$4411,"<"&EDATE(A70,1)) -> 17314.994 | D70: =SUMIFS(Sales_Transactions!$Q$2:$Q$4411,Sales_Transactions!$E$2:$E$4411,"West",Sales_Transactions!$B$2:$B$4411,">="&A70,Sales_Transactions!$B$2:$B$4411,"<"&EDATE(A70,1)) -> 8817.321 | E70: =SUMIFS(Sales_Transactions!$Q$2:$Q$4411,Sales_Transactions!$E$2:$E$4411,"Central",Sales_Transactions!$B$2:$B$4411,">="&A70,Sales_Transactions!$B$2:$B$4411,"<"&EDATE(A70,1)) -> 10956.054 | F70: =SUMIFS(Sales_Transactions!$Q$2:$Q$4411,Sales_Transactions!$E$2:$E$4411,"South",Sales_Transactions!$B$2:$B$4411,">="&A70,Sales_Transactions!$B$2:$B$4411,"<"&EDATE(A70,1)) -> 11523.18
A71: =A43 -> 45505 | B71: =SUMIFS(Sales_Transactions!$Q$2:$Q$4411,Sales_Transactions!$E$2:$E$4411,"North",Sales_Transactions!$B$2:$B$4411,">="&A71,Sales_Transactions!$B$2:$B$4411,"<"&EDATE(A71,1)) -> 21783.045 | C71: =SUMIFS(Sales_Transactions!$Q$2:$Q$4411,Sales_Transactions!$E$2:$E$4411,"East",Sales_Transactions!$B$2:$B$4411,">="&A71,Sales_Transactions!$B$2:$B$4411,"<"&EDATE(A71,1)) -> 15391.428 | D71: =SUMIFS(Sales_Transactions!$Q$2:$Q$4411,Sales_Transactions!$E$2:$E$4411,"West",Sales_Transactions!$B$2:$B$4411,">="&A71,Sales_Transactions!$B$2:$B$4411,"<"&EDATE(A71,1)) -> 15685.664 | E71: =SUMIFS(Sales_Transactions!$Q$2:$Q$4411,Sales_Transactions!$E$2:$E$4411,"Central",Sales_Transactions!$B$2:$B$4411,">="&A71,Sales_Transactions!$B$2:$B$4411,"<"&EDATE(A71,1)) -> 13229.059 | F71: =SUMIFS(Sales_Transactions!$Q$2:$Q$4411,Sales_Transactions!$E$2:$E$4411,"South",Sales_Transactions!$B$2:$B$4411,">="&A71,Sales_Transactions!$B$2:$B$4411,"<"&EDATE(A71,1)) -> 8651.1537
A72: =A44 -> 45536 | B72: =SUMIFS(Sales_Transactions!$Q$2:$Q$4411,Sales_Transactions!$E$2:$E$4411,"North",Sales_Transactions!$B$2:$B$4411,">="&A72,Sales_Transactions!$B$2:$B$4411,"<"&EDATE(A72,1)) -> 11049.006 | C72: =SUMIFS(Sales_Transactions!$Q$2:$Q$4411,Sales_Transactions!$E$2:$E$4411,"East",Sales_Transactions!$B$2:$B$4411,">="&A72,Sales_Transactions!$B$2:$B$4411,"<"&EDATE(A72,1)) -> 13333.043 | D72: =SUMIFS(Sales_Transactions!$Q$2:$Q$4411,Sales_Transactions!$E$2:$E$4411,"West",Sales_Transactions!$B$2:$B$4411,">="&A72,Sales_Transactions!$B$2:$B$4411,"<"&EDATE(A72,1)) -> 10993.077 | E72: =SUMIFS(Sales_Transactions!$Q$2:$Q$4411,Sales_Transactions!$E$2:$E$4411,"Central",Sales_Transactions!$B$2:$B$4411,">="&A72,Sales_Transactions!$B$2:$B$4411,"<"&EDATE(A72,1)) -> 14315.534 | F72: =SUMIFS(Sales_Transactions!$Q$2:$Q$4411,Sales_Transactions!$E$2:$E$4411,"South",Sales_Transactions!$B$2:$B$4411,">="&A72,Sales_Transactions!$B$2:$B$4411,"<"&EDATE(A72,1)) -> 12644.164
A73: =A45 -> 45566 | B73: =SUMIFS(Sales_Transactions!$Q$2:$Q$4411,Sales_Transactions!$E$2:$E$4411,"North",Sales_Transactions!$B$2:$B$4411,">="&A73,Sales_Transactions!$B$2:$B$4411,"<"&EDATE(A73,1)) -> 12998.653 | C73: =SUMIFS(Sales_Transactions!$Q$2:$Q$4411,Sales_Transactions!$E$2:$E$4411,"East",Sales_Transactions!$B$2:$B$4411,">="&A73,Sales_Transactions!$B$2:$B$4411,"<"&EDATE(A73,1)) -> 15074.505 | D73: =SUMIFS(Sales_Transactions!$Q$2:$Q$4411,Sales_Transactions!$E$2:$E$4411,"West",Sales_Transactions!$B$2:$B$4411,">="&A73,Sales_Transactions!$B$2:$B$4411,"<"&EDATE(A73,1)) -> 17870.137 | E73: =SUMIFS(Sales_Transactions!$Q$2:$Q$4411,Sales_Transactions!$E$2:$E$4411,"Central",Sales_Transactions!$B$2:$B$4411,">="&A73,Sales_Transactions!$B$2:$B$4411,"<"&EDATE(A73,1)) -> 10394.628 | F73: =SUMIFS(Sales_Transactions!$Q$2:$Q$4411,Sales_Transactions!$E$2:$E$4411,"South",Sales_Transactions!$B$2:$B$4411,">="&A73,Sales_Transactions!$B$2:$B$4411,"<"&EDATE(A73,1)) -> 15496.736
A74: =A46 -> 45597 | B74: =SUMIFS(Sales_Transactions!$Q$2:$Q$4411,Sales_Transactions!$E$2:$E$4411,"North",Sales_Transactions!$B$2:$B$4411,">="&A74,Sales_Transactions!$B$2:$B$4411,"<"&EDATE(A74,1)) -> 17302.95 | C74: =SUMIFS(Sales_Transactions!$Q$2:$Q$4411,Sales_Transactions!$E$2:$E$4411,"East",Sales_Transactions!$B$2:$B$4411,">="&A74,Sales_Transactions!$B$2:$B$4411,"<"&EDATE(A74,1)) -> 17516.653 | D74: =SUMIFS(Sales_Transactions!$Q$2:$Q$4411,Sales_Transactions!$E$2:$E$4411,"West",Sales_Transactions!$B$2:$B$4411,">="&A74,Sales_Transactions!$B$2:$B$4411,"<"&EDATE(A74,1)) -> 22829.042 | E74: =SUMIFS(Sales_Transactions!$Q$2:$Q$4411,Sales_Transactions!$E$2:$E$4411,"Central",Sales_Transactions!$B$2:$B$4411,">="&A74,Sales_Transactions!$B$2:$B$4411,"<"&EDATE(A74,1)) -> 17468.487 | F74: =SUMIFS(Sales_Transactions!$Q$2:$Q$4411,Sales_Transactions!$E$2:$E$4411,"South",Sales_Transactions!$B$2:$B$4411,">="&A74,Sales_Transactions!$B$2:$B$4411,"<"&EDATE(A74,1)) -> 16216.537
A75: =A47 -> 45627 | B75: =SUMIFS(Sales_Transactions!$Q$2:$Q$4411,Sales_Transactions!$E$2:$E$4411,"North",Sales_Transactions!$B$2:$B$4411,">="&A75,Sales_Transactions!$B$2:$B$4411,"<"&EDATE(A75,1)) -> 29258.633 | C75: =SUMIFS(Sales_Transactions!$Q$2:$Q$4411,Sales_Transactions!$E$2:$E$4411,"East",Sales_Transactions!$B$2:$B$4411,">="&A75,Sales_Transactions!$B$2:$B$4411,"<"&EDATE(A75,1)) -> 38910.857 | D75: =SUMIFS(Sales_Transactions!$Q$2:$Q$4411,Sales_Transactions!$E$2:$E$4411,"West",Sales_Transactions!$B$2:$B$4411,">="&A75,Sales_Transactions!$B$2:$B$4411,"<"&EDATE(A75,1)) -> 15060.462 | E75: =SUMIFS(Sales_Transactions!$Q$2:$Q$4411,Sales_Transactions!$E$2:$E$4411,"Central",Sales_Transactions!$B$2:$B$4411,">="&A75,Sales_Transactions!$B$2:$B$4411,"<"&EDATE(A75,1)) -> 11215.605 | F75: =SUMIFS(Sales_Transactions!$Q$2:$Q$4411,Sales_Transactions!$E$2:$E$4411,"South",Sales_Transactions!$B$2:$B$4411,">="&A75,Sales_Transactions!$B$2:$B$4411,"<"&EDATE(A75,1)) -> 19569.201
... A87: =A59 -> 45992 | B87: =SUMIFS(Sales_Transactions!$Q$2:$Q$4411,Sales_Transactions!$E$2:$E$4411,"North",Sales_Transactions!$B$2:$B$4411,">="&A87,Sales_Transactions!$B$2:$B$4411,"<"&EDATE(A87,1)) -> 31235.71 | C87: =SUMIFS(Sales_Transactions!$Q$2:$Q$4411,Sales_Transactions!$E$2:$E$4411,"East",Sales_Transactions!$B$2:$B$4411,">="&A87,Sales_Transactions!$B$2:$B$4411,"<"&EDATE(A87,1)) -> 39202.796 | D87: =SUMIFS(Sales_Transactions!$Q$2:$Q$4411,Sales_Transactions!$E$2:$E$4411,"West",Sales_Transactions!$B$2:$B$4411,">="&A87,Sales_Transactions!$B$2:$B$4411,"<"&EDATE(A87,1)) -> 27559.39 | E87: =SUMIFS(Sales_Transactions!$Q$2:$Q$4411,Sales_Transactions!$E$2:$E$4411,"Central",Sales_Transactions!$B$2:$B$4411,">="&A87,Sales_Transactions!$B$2:$B$4411,"<"&EDATE(A87,1)) -> 22104.117 | F87: =SUMIFS(Sales_Transactions!$Q$2:$Q$4411,Sales_Transactions!$E$2:$E$4411,"South",Sales_Transactions!$B$2:$B$4411,">="&A87,Sales_Transactions!$B$2:$B$4411,"<"&EDATE(A87,1)) -> 7465.8704
A90: Problem 3 — Region Summary: Revenue vs. Return Rate
A91: Region | B91: Total Revenue | C91: Total Orders | D91: Returned Orders | E91: Return Rate %
A92: North | B92: =SUMIF(Sales_Transactions!$E$2:$E$4411,A92,Sales_Transactions!$Q$2:$Q$4411) -> 476416.1 | C92: =COUNTIF(Sales_Transactions!$E$2:$E$4411,A92) -> 1074 | D92: =COUNTIFS(Sales_Transactions!$E$2:$E$4411,A92,Sales_Transactions!$V$2:$V$4411,"Yes") -> 57 | E92: =D92/C92 -> 0.053072626
A93: East | B93: =SUMIF(Sales_Transactions!$E$2:$E$4411,A93,Sales_Transactions!$Q$2:$Q$4411) -> 421822.05 | C93: =COUNTIF(Sales_Transactions!$E$2:$E$4411,A93) -> 974 | D93: =COUNTIFS(Sales_Transactions!$E$2:$E$4411,A93,Sales_Transactions!$V$2:$V$4411,"Yes") -> 50 | E93: =D93/C93 -> 0.051334702
A94: West | B94: =SUMIF(Sales_Transactions!$E$2:$E$4411,A94,Sales_Transactions!$Q$2:$Q$4411) -> 388209.45 | C94: =COUNTIF(Sales_Transactions!$E$2:$E$4411,A94) -> 900 | D94: =COUNTIFS(Sales_Transactions!$E$2:$E$4411,A94,Sales_Transactions!$V$2:$V$4411,"Yes") -> 57 | E94: =D94/C94 -> 0.063333333
A95: Central | B95: =SUMIF(Sales_Transactions!$E$2:$E$4411,A95,Sales_Transactions!$Q$2:$Q$4411) -> 340849.85 | C95: =COUNTIF(Sales_Transactions!$E$2:$E$4411,A95) -> 777 | D95: =COUNTIFS(Sales_Transactions!$E$2:$E$4411,A95,Sales_Transactions!$V$2:$V$4411,"Yes") -> 39 | E95: =D95/C95 -> 0.05019305
A96: South | B96: =SUMIF(Sales_Transactions!$E$2:$E$4411,A96,Sales_Transactions!$Q$2:$Q$4411) -> 318328.63 | C96: =COUNTIF(Sales_Transactions!$E$2:$E$4411,A96) -> 685 | D96: =COUNTIFS(Sales_Transactions!$E$2:$E$4411,A96,Sales_Transactions!$V$2:$V$4411,"Yes") -> 148 | E96: =D96/C96 -> 0.21605839
